{
    "data": [
        {
            "strDistrito": "",
            "idtipoorgpolitica": 1,
            "strTipoOrgPolitica": "PARTIDOS POLITICOS",
            "idOrganizacionPolitica": 14,
            "strOrganizacionPolitica": "PARTIDO DEMOCRATICO SOMOS PERU",
            "idJuradoElectoralCreacion": 2103,
            "strJuradoElectoralCreacion": "MARISCAL NIETO",
            "intPosicion": 2,
            "idCargo": 16,
            "strCargo": "SENADOR",
            "strTipoDocumento": "DNI",
            "strDocumentoIdentidad": "10244829",
            "strNombres": "JANET MONICA",
            "strApellidoPaterno": "BERRIOS",
            "strApellidoMaterno": "SUAREZ",
            "strSexo": "FEMENINO",
            "strFechaNacimiento": "6/12/1973 00:00:00",
            "strEsNativo": "NO",
            "strEstadoCandidato": "INSCRITO",
            "strGuidFoto": "c62e422a-fba8-4864-849c-1f1ce8546416",
            "strNombre": "c62e422a-fba8-4864-849c-1f1ce8546416.jpg",
            "strUrlOrganizacionPolitica": "",
            "strCodExpedienteExt": "EG.2026016718",
            "idProcesoElectoral": 124,
            "strProcesoElectoral": "ELECCIONES GENERALES 2026",
            "idTipoEleccion": 21,
            "strTipoEleccion": "SENADORES DISTRITO MÚLTIPLE",
            "strAmbito": "NACIONAL",
            "strAnio_Eleccion": "2026",
            "strUbigeo": "170000",
            "strDepartamento": "MOQUEGUA",
            "strProvincia": ""
        },
        {
            "strDistrito": "",
            "idtipoorgpolitica": 5,
            "strTipoOrgPolitica": "ALIANZAS ELECTORALES",
            "idOrganizacionPolitica": 3025,
            "strOrganizacionPolitica": "ALIANZA ELECTORAL VENCEREMOS",
            "idJuradoElectoralCreacion": 2103,
            "strJuradoElectoralCreacion": "MARISCAL NIETO",
            "intPosicion": 2,
            "idCargo": 16,
            "strCargo": "SENADOR",
            "strTipoDocumento": "DNI",
            "strDocumentoIdentidad": "04721831",
            "strNombres": "MARIA CLEOTILDE",
            "strApellidoPaterno": "CHIRE",
            "strApellidoMaterno": "PORRAS",
            "strSexo": "FEMENINO",
            "strFechaNacimiento": "3/06/1960 00:00:00",
            "strEsNativo": "NO",
            "strEstadoCandidato": "INSCRITO",
            "strGuidFoto": "582fb012-551a-4f7d-a100-52178453c852",
            "strNombre": "582fb012-551a-4f7d-a100-52178453c852.jpg",
            "strUrlOrganizacionPolitica": "",
            "strCodExpedienteExt": "EG.2026016540",
            "idProcesoElectoral": 124,
            "strProcesoElectoral": "ELECCIONES GENERALES 2026",
            "idTipoEleccion": 21,
            "strTipoEleccion": "SENADORES DISTRITO MÚLTIPLE",
            "strAmbito": "NACIONAL",
            "strAnio_Eleccion": "2026",
            "strUbigeo": "170000",
            "strDepartamento": "",
            "strProvincia": ""
        },
        {
            "strDistrito": "",
            "idtipoorgpolitica": 1,
            "strTipoOrgPolitica": "PARTIDOS POLITICOS",
            "idOrganizacionPolitica": 22,
            "strOrganizacionPolitica": "RENOVACION POPULAR",
            "idJuradoElectoralCreacion": 2103,
            "strJuradoElectoralCreacion": "MARISCAL NIETO",
            "intPosicion": 1,
            "idCargo": 16,
            "strCargo": "SENADOR",
            "strTipoDocumento": "DNI-E",
            "strDocumentoIdentidad": "43295002",
            "strNombres": "CARLOS ANTONIO",
            "strApellidoPaterno": "RIVERA",
            "strApellidoMaterno": "BECERRA",
            "strSexo": "MASCULINO",
            "strFechaNacimiento": "2/03/1957 00:00:00",
            "strEsNativo": "NO",
            "strEstadoCandidato": "INSCRITO",
            "strGuidFoto": "84fcc241-2fc4-4347-9f6a-94ef7a14d195",
            "strNombre": "84fcc241-2fc4-4347-9f6a-94ef7a14d195.jpg",
            "strUrlOrganizacionPolitica": "",
            "strCodExpedienteExt": "EG.2026015586",
            "idProcesoElectoral": 124,
            "strProcesoElectoral": "ELECCIONES GENERALES 2026",
            "idTipoEleccion": 21,
            "strTipoEleccion": "SENADORES DISTRITO MÚLTIPLE",
            "strAmbito": "NACIONAL",
            "strAnio_Eleccion": "2026",
            "strUbigeo": "170000",
            "strDepartamento": "MOQUEGUA",
            "strProvincia": ""
        },
        {
            "strDistrito": "",
            "idtipoorgpolitica": 1,
            "strTipoOrgPolitica": "PARTIDOS POLITICOS",
            "idOrganizacionPolitica": 22,
            "strOrganizacionPolitica": "RENOVACION POPULAR",
            "idJuradoElectoralCreacion": 2103,
            "strJuradoElectoralCreacion": "MARISCAL NIETO",
            "intPosicion": 2,
            "idCargo": 16,
            "strCargo": "SENADOR",
            "strTipoDocumento": "DNI",
            "strDocumentoIdentidad": "04627906",
            "strNombres": "SANTOS MARIA HORTENSIA",
            "strApellidoPaterno": "MACKENZCE",
            "strApellidoMaterno": "DE LUNA",
            "strSexo": "FEMENINO",
            "strFechaNacimiento": "1/11/1957 00:00:00",
            "strEsNativo": "NO",
            "strEstadoCandidato": "INSCRITO",
            "strGuidFoto": "6dd52112-174d-43ad-a0bc-ff8ff3ecf3fd",
            "strNombre": "6dd52112-174d-43ad-a0bc-ff8ff3ecf3fd.jpg",
            "strUrlOrganizacionPolitica": "",
            "strCodExpedienteExt": "EG.2026015586",
            "idProcesoElectoral": 124,
            "strProcesoElectoral": "ELECCIONES GENERALES 2026",
            "idTipoEleccion": 21,
            "strTipoEleccion": "SENADORES DISTRITO MÚLTIPLE",
            "strAmbito": "NACIONAL",
            "strAnio_Eleccion": "2026",
            "strUbigeo": "170000",
            "strDepartamento": "MOQUEGUA",
            "strProvincia": ""
        },
        {
            "strDistrito": "",
            "idtipoorgpolitica": 1,
            "strTipoOrgPolitica": "PARTIDOS POLITICOS",
            "idOrganizacionPolitica": 1257,
            "strOrganizacionPolitica": "ALIANZA PARA EL PROGRESO",
            "idJuradoElectoralCreacion": 2103,
            "strJuradoElectoralCreacion": "MARISCAL NIETO",
            "intPosicion": 1,
            "idCargo": 16,
            "strCargo": "SENADOR",
            "strTipoDocumento": "DNI",
            "strDocumentoIdentidad": "01215784",
            "strNombres": "LUDGARDO",
            "strApellidoPaterno": "VENEGAS",
            "strApellidoMaterno": "SOTOMAYOR",
            "strSexo": "MASCULINO",
            "strFechaNacimiento": "16/06/1953 00:00:00",
            "strEsNativo": "NO",
            "strEstadoCandidato": "INSCRITO",
            "strGuidFoto": "9a7fb2b1-0f79-4592-9bd8-0faf7d8e07ce",
            "strNombre": "9a7fb2b1-0f79-4592-9bd8-0faf7d8e07ce.jpg",
            "strUrlOrganizacionPolitica": "",
            "strCodExpedienteExt": "EG.2026015552",
            "idProcesoElectoral": 124,
            "strProcesoElectoral": "ELECCIONES GENERALES 2026",
            "idTipoEleccion": 21,
            "strTipoEleccion": "SENADORES DISTRITO MÚLTIPLE",
            "strAmbito": "NACIONAL",
            "strAnio_Eleccion": "2026",
            "strUbigeo": "170000",
            "strDepartamento": "MOQUEGUA",
            "strProvincia": ""
        },
        {
            "strDistrito": "",
            "idtipoorgpolitica": 1,
            "strTipoOrgPolitica": "PARTIDOS POLITICOS",
            "idOrganizacionPolitica": 1257,
            "strOrganizacionPolitica": "ALIANZA PARA EL PROGRESO",
            "idJuradoElectoralCreacion": 2103,
            "strJuradoElectoralCreacion": "MARISCAL NIETO",
            "intPosicion": 2,
            "idCargo": 16,
            "strCargo": "SENADOR",
            "strTipoDocumento": "DNI",
            "strDocumentoIdentidad": "04431434",
            "strNombres": "DAYENA GRACIELA",
            "strApellidoPaterno": "TACO",
            "strApellidoMaterno": "TALA",
            "strSexo": "FEMENINO",
            "strFechaNacimiento": "17/10/1972 00:00:00",
            "strEsNativo": "NO",
            "strEstadoCandidato": "INSCRITO",
            "strGuidFoto": "18f31530-7a0b-4ced-b754-b2eba54bdb21",
            "strNombre": "18f31530-7a0b-4ced-b754-b2eba54bdb21.jpg",
            "strUrlOrganizacionPolitica": "",
            "strCodExpedienteExt": "EG.2026015552",
            "idProcesoElectoral": 124,
            "strProcesoElectoral": "ELECCIONES GENERALES 2026",
            "idTipoEleccion": 21,
            "strTipoEleccion": "SENADORES DISTRITO MÚLTIPLE",
            "strAmbito": "NACIONAL",
            "strAnio_Eleccion": "2026",
            "strUbigeo": "170000",
            "strDepartamento": "MOQUEGUA",
            "strProvincia": ""
        },
        {
            "strDistrito": "",
            "idtipoorgpolitica": 1,
            "strTipoOrgPolitica": "PARTIDOS POLITICOS",
            "idOrganizacionPolitica": 1264,
            "strOrganizacionPolitica": "JUNTOS POR EL PERU",
            "idJuradoElectoralCreacion": 2103,
            "strJuradoElectoralCreacion": "MARISCAL NIETO",
            "intPosicion": 2,
            "idCargo": 16,
            "strCargo": "SENADOR",
            "strTipoDocumento": "DNI",
            "strDocumentoIdentidad": "04436234",
            "strNombres": "GRACIELA NORMA",
            "strApellidoPaterno": "VIZA",
            "strApellidoMaterno": "HUIZA",
            "strSexo": "FEMENINO",
            "strFechaNacimiento": "1/01/1969 00:00:00",
            "strEsNativo": "NO",
            "strEstadoCandidato": "IMPROCEDENTE",
            "strGuidFoto": "cfeff592-82b8-47e7-8bd6-a3d2e60695cd",
            "strNombre": "cfeff592-82b8-47e7-8bd6-a3d2e60695cd.jpg",
            "strUrlOrganizacionPolitica": "",
            "strCodExpedienteExt": "EG.2026016738",
            "idProcesoElectoral": 124,
            "strProcesoElectoral": "ELECCIONES GENERALES 2026",
            "idTipoEleccion": 21,
            "strTipoEleccion": "SENADORES DISTRITO MÚLTIPLE",
            "strAmbito": "NACIONAL",
            "strAnio_Eleccion": "2026",
            "strUbigeo": "170000",
            "strDepartamento": "MOQUEGUA",
            "strProvincia": ""
        },
        {
            "strDistrito": "",
            "idtipoorgpolitica": 1,
            "strTipoOrgPolitica": "PARTIDOS POLITICOS",
            "idOrganizacionPolitica": 1264,
            "strOrganizacionPolitica": "JUNTOS POR EL PERU",
            "idJuradoElectoralCreacion": 2103,
            "strJuradoElectoralCreacion": "MARISCAL NIETO",
            "intPosicion": 1,
            "idCargo": 16,
            "strCargo": "SENADOR",
            "strTipoDocumento": "DNI",
            "strDocumentoIdentidad": "04647085",
            "strNombres": "VICTOR RAUL",
            "strApellidoPaterno": "CUTIPA",
            "strApellidoMaterno": "CCAMA",
            "strSexo": "MASCULINO",
            "strFechaNacimiento": "14/09/1972 00:00:00",
            "strEsNativo": "NO",
            "strEstadoCandidato": "INSCRITO",
            "strGuidFoto": "8a462ad7-557a-40c5-80af-4f87c81544ea",
            "strNombre": "8a462ad7-557a-40c5-80af-4f87c81544ea.jpg",
            "strUrlOrganizacionPolitica": "",
            "strCodExpedienteExt": "EG.2026016738",
            "idProcesoElectoral": 124,
            "strProcesoElectoral": "ELECCIONES GENERALES 2026",
            "idTipoEleccion": 21,
            "strTipoEleccion": "SENADORES DISTRITO MÚLTIPLE",
            "strAmbito": "NACIONAL",
            "strAnio_Eleccion": "2026",
            "strUbigeo": "170000",
            "strDepartamento": "MOQUEGUA",
            "strProvincia": ""
        },
        {
            "strDistrito": "",
            "idtipoorgpolitica": 1,
            "strTipoOrgPolitica": "PARTIDOS POLITICOS",
            "idOrganizacionPolitica": 1366,
            "strOrganizacionPolitica": "FUERZA POPULAR",
            "idJuradoElectoralCreacion": 2103,
            "strJuradoElectoralCreacion": "MARISCAL NIETO",
            "intPosicion": 2,
            "idCargo": 16,
            "strCargo": "SENADOR",
            "strTipoDocumento": "DNI",
            "strDocumentoIdentidad": "04409052",
            "strNombres": "CECILIA FILOMENA",
            "strApellidoPaterno": "LAURA",
            "strApellidoMaterno": "MAMANI",
            "strSexo": "FEMENINO",
            "strFechaNacimiento": "22/11/1961 00:00:00",
            "strEsNativo": "NO",
            "strEstadoCandidato": "INSCRITO",
            "strGuidFoto": "ec1ec92e-d8d8-4107-a6b1-1006c1d4b0a9",
            "strNombre": "ec1ec92e-d8d8-4107-a6b1-1006c1d4b0a9.jpg",
            "strUrlOrganizacionPolitica": "",
            "strCodExpedienteExt": "EG.2026015428",
            "idProcesoElectoral": 124,
            "strProcesoElectoral": "ELECCIONES GENERALES 2026",
            "idTipoEleccion": 21,
            "strTipoEleccion": "SENADORES DISTRITO MÚLTIPLE",
            "strAmbito": "NACIONAL",
            "strAnio_Eleccion": "2026",
            "strUbigeo": "170000",
            "strDepartamento": "MOQUEGUA",
            "strProvincia": ""
        },
        {
            "strDistrito": "",
            "idtipoorgpolitica": 1,
            "strTipoOrgPolitica": "PARTIDOS POLITICOS",
            "idOrganizacionPolitica": 1366,
            "strOrganizacionPolitica": "FUERZA POPULAR",
            "idJuradoElectoralCreacion": 2103,
            "strJuradoElectoralCreacion": "MARISCAL NIETO",
            "intPosicion": 1,
            "idCargo": 16,
            "strCargo": "SENADOR",
            "strTipoDocumento": "DNI",
            "strDocumentoIdentidad": "29394406",
            "strNombres": "MARIO FIDEL",
            "strApellidoPaterno": "MANTILLA",
            "strApellidoMaterno": "MEDINA",
            "strSexo": "MASCULINO",
            "strFechaNacimiento": "22/07/1960 00:00:00",
            "strEsNativo": "NO",
            "strEstadoCandidato": "INSCRITO",
            "strGuidFoto": "9beefea4-3f6e-49f0-96ce-9487f003b3b2",
            "strNombre": "9beefea4-3f6e-49f0-96ce-9487f003b3b2.jpg",
            "strUrlOrganizacionPolitica": "",
            "strCodExpedienteExt": "EG.2026015428",
            "idProcesoElectoral": 124,
            "strProcesoElectoral": "ELECCIONES GENERALES 2026",
            "idTipoEleccion": 21,
            "strTipoEleccion": "SENADORES DISTRITO MÚLTIPLE",
            "strAmbito": "NACIONAL",
            "strAnio_Eleccion": "2026",
            "strUbigeo": "170000",
            "strDepartamento": "MOQUEGUA",
            "strProvincia": ""
        },
        {
            "strDistrito": "",
            "idtipoorgpolitica": 1,
            "strTipoOrgPolitica": "PARTIDOS POLITICOS",
            "idOrganizacionPolitica": 2840,
            "strOrganizacionPolitica": "PARTIDO MORADO",
            "idJuradoElectoralCreacion": 2103,
            "strJuradoElectoralCreacion": "MARISCAL NIETO",
            "intPosicion": 2,
            "idCargo": 16,
            "strCargo": "SENADOR",
            "strTipoDocumento": "DNI",
            "strDocumentoIdentidad": "04648075",
            "strNombres": "BENILDA YANETH",
            "strApellidoPaterno": "GUERRERO",
            "strApellidoMaterno": "PILCO",
            "strSexo": "FEMENINO",
            "strFechaNacimiento": "10/11/1971 00:00:00",
            "strEsNativo": "NO",
            "strEstadoCandidato": "INSCRITO",
            "strGuidFoto": "f2478e11-f0de-47a4-ab68-ca2ece06542a",
            "strNombre": "f2478e11-f0de-47a4-ab68-ca2ece06542a.jpg",
            "strUrlOrganizacionPolitica": "",
            "strCodExpedienteExt": "EG.2026017133",
            "idProcesoElectoral": 124,
            "strProcesoElectoral": "ELECCIONES GENERALES 2026",
            "idTipoEleccion": 21,
            "strTipoEleccion": "SENADORES DISTRITO MÚLTIPLE",
            "strAmbito": "NACIONAL",
            "strAnio_Eleccion": "2026",
            "strUbigeo": "170000",
            "strDepartamento": "MOQUEGUA",
            "strProvincia": ""
        },
        {
            "strDistrito": "",
            "idtipoorgpolitica": 1,
            "strTipoOrgPolitica": "PARTIDOS POLITICOS",
            "idOrganizacionPolitica": 2840,
            "strOrganizacionPolitica": "PARTIDO MORADO",
            "idJuradoElectoralCreacion": 2103,
            "strJuradoElectoralCreacion": "MARISCAL NIETO",
            "intPosicion": 1,
            "idCargo": 16,
            "strCargo": "SENADOR",
            "strTipoDocumento": "DNI",
            "strDocumentoIdentidad": "04417334",
            "strNombres": "FERNANDO GREGORY",
            "strApellidoPaterno": "MARTINEZ",
            "strApellidoMaterno": "HUMIRE",
            "strSexo": "MASCULINO",
            "strFechaNacimiento": "16/03/1962 00:00:00",
            "strEsNativo": "NO",
            "strEstadoCandidato": "INSCRITO",
            "strGuidFoto": "d91c47e3-b58e-4a90-acb4-7f7eecfbb6d7",
            "strNombre": "d91c47e3-b58e-4a90-acb4-7f7eecfbb6d7.jpg",
            "strUrlOrganizacionPolitica": "",
            "strCodExpedienteExt": "EG.2026017133",
            "idProcesoElectoral": 124,
            "strProcesoElectoral": "ELECCIONES GENERALES 2026",
            "idTipoEleccion": 21,
            "strTipoEleccion": "SENADORES DISTRITO MÚLTIPLE",
            "strAmbito": "NACIONAL",
            "strAnio_Eleccion": "2026",
            "strUbigeo": "170000",
            "strDepartamento": "MOQUEGUA",
            "strProvincia": ""
        },
        {
            "strDistrito": "",
            "idtipoorgpolitica": 1,
            "strTipoOrgPolitica": "PARTIDOS POLITICOS",
            "idOrganizacionPolitica": 2857,
            "strOrganizacionPolitica": "PARTIDO FRENTE DE LA ESPERANZA 2021",
            "idJuradoElectoralCreacion": 2103,
            "strJuradoElectoralCreacion": "MARISCAL NIETO",
            "intPosicion": 2,
            "idCargo": 16,
            "strCargo": "SENADOR",
            "strTipoDocumento": "DNI",
            "strDocumentoIdentidad": "04629488",
            "strNombres": "RAUL ARCIBIADES",
            "strApellidoPaterno": "ZEVALLOS",
            "strApellidoMaterno": "ESPINOZA",
            "strSexo": "MASCULINO",
            "strFechaNacimiento": "24/09/1961 00:00:00",
            "strEsNativo": "NO",
            "strEstadoCandidato": "INSCRITO",
            "strGuidFoto": "e04d6cd5-1e98-4975-8e59-bdb255a3173c",
            "strNombre": "e04d6cd5-1e98-4975-8e59-bdb255a3173c.jpg",
            "strUrlOrganizacionPolitica": "",
            "strCodExpedienteExt": "EG.2026016591",
            "idProcesoElectoral": 124,
            "strProcesoElectoral": "ELECCIONES GENERALES 2026",
            "idTipoEleccion": 21,
            "strTipoEleccion": "SENADORES DISTRITO MÚLTIPLE",
            "strAmbito": "NACIONAL",
            "strAnio_Eleccion": "2026",
            "strUbigeo": "170000",
            "strDepartamento": "MOQUEGUA",
            "strProvincia": ""
        },
        {
            "strDistrito": "",
            "idtipoorgpolitica": 1,
            "strTipoOrgPolitica": "PARTIDOS POLITICOS",
            "idOrganizacionPolitica": 2857,
            "strOrganizacionPolitica": "PARTIDO FRENTE DE LA ESPERANZA 2021",
            "idJuradoElectoralCreacion": 2103,
            "strJuradoElectoralCreacion": "MARISCAL NIETO",
            "intPosicion": 1,
            "idCargo": 16,
            "strCargo": "SENADOR",
            "strTipoDocumento": "DNI",
            "strDocumentoIdentidad": "04438689",
            "strNombres": "PAMELA INDIRA",
            "strApellidoPaterno": "BLAS",
            "strApellidoMaterno": "CASTRO",
            "strSexo": "FEMENINO",
            "strFechaNacimiento": "27/07/1977 00:00:00",
            "strEsNativo": "NO",
            "strEstadoCandidato": "INSCRITO",
            "strGuidFoto": "e39fb879-a1f0-4cf2-ae3c-c5bf62f57599",
            "strNombre": "e39fb879-a1f0-4cf2-ae3c-c5bf62f57599.jpg",
            "strUrlOrganizacionPolitica": "",
            "strCodExpedienteExt": "EG.2026016591",
            "idProcesoElectoral": 124,
            "strProcesoElectoral": "ELECCIONES GENERALES 2026",
            "idTipoEleccion": 21,
            "strTipoEleccion": "SENADORES DISTRITO MÚLTIPLE",
            "strAmbito": "NACIONAL",
            "strAnio_Eleccion": "2026",
            "strUbigeo": "170000",
            "strDepartamento": "MOQUEGUA",
            "strProvincia": ""
        },
        {
            "strDistrito": "",
            "idtipoorgpolitica": 1,
            "strTipoOrgPolitica": "PARTIDOS POLITICOS",
            "idOrganizacionPolitica": 2173,
            "strOrganizacionPolitica": "AVANZA PAIS - PARTIDO DE INTEGRACION SOCIAL",
            "idJuradoElectoralCreacion": 2103,
            "strJuradoElectoralCreacion": "MARISCAL NIETO",
            "intPosicion": 2,
            "idCargo": 16,
            "strCargo": "SENADOR",
            "strTipoDocumento": "DNI",
            "strDocumentoIdentidad": "09558864",
            "strNombres": "EDGAR",
            "strApellidoPaterno": "RAFAEL",
            "strApellidoMaterno": "ROMERO",
            "strSexo": "MASCULINO",
            "strFechaNacimiento": "27/09/1968 00:00:00",
            "strEsNativo": "NO",
            "strEstadoCandidato": "IMPROCEDENTE",
            "strGuidFoto": "487a7b35-60dd-4728-8703-2e3b96bcc6ab",
            "strNombre": "487a7b35-60dd-4728-8703-2e3b96bcc6ab.jpg",
            "strUrlOrganizacionPolitica": "",
            "strCodExpedienteExt": "EG.2026016271",
            "idProcesoElectoral": 124,
            "strProcesoElectoral": "ELECCIONES GENERALES 2026",
            "idTipoEleccion": 21,
            "strTipoEleccion": "SENADORES DISTRITO MÚLTIPLE",
            "strAmbito": "NACIONAL",
            "strAnio_Eleccion": "2026",
            "strUbigeo": "170000",
            "strDepartamento": "MOQUEGUA",
            "strProvincia": ""
        },
        {
            "strDistrito": "",
            "idtipoorgpolitica": 1,
            "strTipoOrgPolitica": "PARTIDOS POLITICOS",
            "idOrganizacionPolitica": 2173,
            "strOrganizacionPolitica": "AVANZA PAIS - PARTIDO DE INTEGRACION SOCIAL",
            "idJuradoElectoralCreacion": 2103,
            "strJuradoElectoralCreacion": "MARISCAL NIETO",
            "intPosicion": 1,
            "idCargo": 16,
            "strCargo": "SENADOR",
            "strTipoDocumento": "DNI",
            "strDocumentoIdentidad": "08773727",
            "strNombres": "ROSARIO M.DE FATIMA",
            "strApellidoPaterno": "OLIVAS",
            "strApellidoMaterno": "WESTON",
            "strSexo": "FEMENINO",
            "strFechaNacimiento": "30/10/1957 00:00:00",
            "strEsNativo": "NO",
            "strEstadoCandidato": "INSCRITO",
            "strGuidFoto": "c85cc5fc-b660-4986-bd87-c8dbe7e9134a",
            "strNombre": "c85cc5fc-b660-4986-bd87-c8dbe7e9134a.jpg",
            "strUrlOrganizacionPolitica": "",
            "strCodExpedienteExt": "EG.2026016271",
            "idProcesoElectoral": 124,
            "strProcesoElectoral": "ELECCIONES GENERALES 2026",
            "idTipoEleccion": 21,
            "strTipoEleccion": "SENADORES DISTRITO MÚLTIPLE",
            "strAmbito": "NACIONAL",
            "strAnio_Eleccion": "2026",
            "strUbigeo": "170000",
            "strDepartamento": "MOQUEGUA",
            "strProvincia": ""
        },
        {
            "strDistrito": "",
            "idtipoorgpolitica": 1,
            "strTipoOrgPolitica": "PARTIDOS POLITICOS",
            "idOrganizacionPolitica": 2218,
            "strOrganizacionPolitica": "PARTIDO POLITICO NACIONAL PERU LIBRE",
            "idJuradoElectoralCreacion": 2103,
            "strJuradoElectoralCreacion": "MARISCAL NIETO",
            "intPosicion": 2,
            "idCargo": 16,
            "strCargo": "SENADOR",
            "strTipoDocumento": "DNI",
            "strDocumentoIdentidad": "04437979",
            "strNombres": "YENY SOLEDAD",
            "strApellidoPaterno": "FLORES",
            "strApellidoMaterno": "SILVA",
            "strSexo": "FEMENINO",
            "strFechaNacimiento": "21/06/1977 00:00:00",
            "strEsNativo": "NO",
            "strEstadoCandidato": "INSCRITO",
            "strGuidFoto": "d076b52f-bfd0-473b-aaeb-1acbf98b395d",
            "strNombre": "d076b52f-bfd0-473b-aaeb-1acbf98b395d.jpg",
            "strUrlOrganizacionPolitica": "",
            "strCodExpedienteExt": "EG.2026015444",
            "idProcesoElectoral": 124,
            "strProcesoElectoral": "ELECCIONES GENERALES 2026",
            "idTipoEleccion": 21,
            "strTipoEleccion": "SENADORES DISTRITO MÚLTIPLE",
            "strAmbito": "NACIONAL",
            "strAnio_Eleccion": "2026",
            "strUbigeo": "170000",
            "strDepartamento": "MOQUEGUA",
            "strProvincia": ""
        },
        {
            "strDistrito": "",
            "idtipoorgpolitica": 1,
            "strTipoOrgPolitica": "PARTIDOS POLITICOS",
            "idOrganizacionPolitica": 2218,
            "strOrganizacionPolitica": "PARTIDO POLITICO NACIONAL PERU LIBRE",
            "idJuradoElectoralCreacion": 2103,
            "strJuradoElectoralCreacion": "MARISCAL NIETO",
            "intPosicion": 1,
            "idCargo": 16,
            "strCargo": "SENADOR",
            "strTipoDocumento": "DNI",
            "strDocumentoIdentidad": "04743412",
            "strNombres": "DAVID FRANCISCO",
            "strApellidoPaterno": "MAMANI",
            "strApellidoMaterno": "GUTIERREZ",
            "strSexo": "MASCULINO",
            "strFechaNacimiento": "9/08/1974 00:00:00",
            "strEsNativo": "NO",
            "strEstadoCandidato": "INSCRITO",
            "strGuidFoto": "d94d8b7a-8e2f-48c0-9777-0e0a4a829dec",
            "strNombre": "d94d8b7a-8e2f-48c0-9777-0e0a4a829dec.jpg",
            "strUrlOrganizacionPolitica": "",
            "strCodExpedienteExt": "EG.2026015444",
            "idProcesoElectoral": 124,
            "strProcesoElectoral": "ELECCIONES GENERALES 2026",
            "idTipoEleccion": 21,
            "strTipoEleccion": "SENADORES DISTRITO MÚLTIPLE",
            "strAmbito": "NACIONAL",
            "strAnio_Eleccion": "2026",
            "strUbigeo": "170000",
            "strDepartamento": "MOQUEGUA",
            "strProvincia": ""
        },
        {
            "strDistrito": "",
            "idtipoorgpolitica": 1,
            "strTipoOrgPolitica": "PARTIDOS POLITICOS",
            "idOrganizacionPolitica": 2939,
            "strOrganizacionPolitica": "PARTIDO DE LOS TRABAJADORES Y EMPRENDEDORES PTE - PERU",
            "idJuradoElectoralCreacion": 2103,
            "strJuradoElectoralCreacion": "MARISCAL NIETO",
            "intPosicion": 1,
            "idCargo": 16,
            "strCargo": "SENADOR",
            "strTipoDocumento": "DNI-E",
            "strDocumentoIdentidad": "04412201",
            "strNombres": "CIPRIANO TEODOSIO",
            "strApellidoPaterno": "ZAMBRANO",
            "strApellidoMaterno": "CAMA",
            "strSexo": "MASCULINO",
            "strFechaNacimiento": "26/09/1948 00:00:00",
            "strEsNativo": "NO",
            "strEstadoCandidato": "IMPROCEDENTE",
            "strGuidFoto": "18bfe7c7-d49f-437c-aa42-457c62d645c8",
            "strNombre": "18bfe7c7-d49f-437c-aa42-457c62d645c8.jpg",
            "strUrlOrganizacionPolitica": "",
            "strCodExpedienteExt": "EG.2026017676",
            "idProcesoElectoral": 124,
            "strProcesoElectoral": "ELECCIONES GENERALES 2026",
            "idTipoEleccion": 21,
            "strTipoEleccion": "SENADORES DISTRITO MÚLTIPLE",
            "strAmbito": "NACIONAL",
            "strAnio_Eleccion": "2026",
            "strUbigeo": "170000",
            "strDepartamento": "MOQUEGUA",
            "strProvincia": ""
        },
        {
            "strDistrito": "",
            "idtipoorgpolitica": 1,
            "strTipoOrgPolitica": "PARTIDOS POLITICOS",
            "idOrganizacionPolitica": 2939,
            "strOrganizacionPolitica": "PARTIDO DE LOS TRABAJADORES Y EMPRENDEDORES PTE - PERU",
            "idJuradoElectoralCreacion": 2103,
            "strJuradoElectoralCreacion": "MARISCAL NIETO",
            "intPosicion": 2,
            "idCargo": 16,
            "strCargo": "SENADOR",
            "strTipoDocumento": "DNI",
            "strDocumentoIdentidad": "04647238",
            "strNombres": "ELIZABETH ROSARIO",
            "strApellidoPaterno": "PACHECO",
            "strApellidoMaterno": "UGARTE",
            "strSexo": "FEMENINO",
            "strFechaNacimiento": "2/05/1972 00:00:00",
            "strEsNativo": "NO",
            "strEstadoCandidato": "IMPROCEDENTE",
            "strGuidFoto": "971d01b9-d9f5-4a88-9d15-eb732144d290",
            "strNombre": "971d01b9-d9f5-4a88-9d15-eb732144d290.jpg",
            "strUrlOrganizacionPolitica": "",
            "strCodExpedienteExt": "EG.2026017676",
            "idProcesoElectoral": 124,
            "strProcesoElectoral": "ELECCIONES GENERALES 2026",
            "idTipoEleccion": 21,
            "strTipoEleccion": "SENADORES DISTRITO MÚLTIPLE",
            "strAmbito": "NACIONAL",
            "strAnio_Eleccion": "2026",
            "strUbigeo": "170000",
            "strDepartamento": "MOQUEGUA",
            "strProvincia": ""
        },
        {
            "strDistrito": "",
            "idtipoorgpolitica": 1,
            "strTipoOrgPolitica": "PARTIDOS POLITICOS",
            "idOrganizacionPolitica": 2933,
            "strOrganizacionPolitica": "LIBERTAD POPULAR",
            "idJuradoElectoralCreacion": 2103,
            "strJuradoElectoralCreacion": "MARISCAL NIETO",
            "intPosicion": 1,
            "idCargo": 16,
            "strCargo": "SENADOR",
            "strTipoDocumento": "DNI",
            "strDocumentoIdentidad": "22505705",
            "strNombres": "MARIA MAGDALENA",
            "strApellidoPaterno": "CHAVEZ",
            "strApellidoMaterno": "SAAVEDRA",
            "strSexo": "FEMENINO",
            "strFechaNacimiento": "7/09/1975 00:00:00",
            "strEsNativo": "NO",
            "strEstadoCandidato": "IMPROCEDENTE",
            "strGuidFoto": "9dcc07c3-0cf4-4af4-9615-d8691eb9a6db",
            "strNombre": "9dcc07c3-0cf4-4af4-9615-d8691eb9a6db.jpg",
            "strUrlOrganizacionPolitica": "",
            "strCodExpedienteExt": "EG.2026016247",
            "idProcesoElectoral": 124,
            "strProcesoElectoral": "ELECCIONES GENERALES 2026",
            "idTipoEleccion": 21,
            "strTipoEleccion": "SENADORES DISTRITO MÚLTIPLE",
            "strAmbito": "NACIONAL",
            "strAnio_Eleccion": "2026",
            "strUbigeo": "170000",
            "strDepartamento": "MOQUEGUA",
            "strProvincia": ""
        },
        {
            "strDistrito": "",
            "idtipoorgpolitica": 1,
            "strTipoOrgPolitica": "PARTIDOS POLITICOS",
            "idOrganizacionPolitica": 2933,
            "strOrganizacionPolitica": "LIBERTAD POPULAR",
            "idJuradoElectoralCreacion": 2103,
            "strJuradoElectoralCreacion": "MARISCAL NIETO",
            "intPosicion": 2,
            "idCargo": 16,
            "strCargo": "SENADOR",
            "strTipoDocumento": "DNI",
            "strDocumentoIdentidad": "09481703",
            "strNombres": "RICHARD MELESIO",
            "strApellidoPaterno": "QUEZADA",
            "strApellidoMaterno": "PASTUSO",
            "strSexo": "MASCULINO",
            "strFechaNacimiento": "18/07/1969 00:00:00",
            "strEsNativo": "NO",
            "strEstadoCandidato": "INSCRITO",
            "strGuidFoto": "b1bd5c68-cbe3-47ba-8232-35732242f18e",
            "strNombre": "b1bd5c68-cbe3-47ba-8232-35732242f18e.jpg",
            "strUrlOrganizacionPolitica": "",
            "strCodExpedienteExt": "EG.2026016247",
            "idProcesoElectoral": 124,
            "strProcesoElectoral": "ELECCIONES GENERALES 2026",
            "idTipoEleccion": 21,
            "strTipoEleccion": "SENADORES DISTRITO MÚLTIPLE",
            "strAmbito": "NACIONAL",
            "strAnio_Eleccion": "2026",
            "strUbigeo": "170000",
            "strDepartamento": "MOQUEGUA",
            "strProvincia": ""
        },
        {
            "strDistrito": "",
            "idtipoorgpolitica": 1,
            "strTipoOrgPolitica": "PARTIDOS POLITICOS",
            "idOrganizacionPolitica": 2930,
            "strOrganizacionPolitica": "PARTIDO APRISTA PERUANO",
            "idJuradoElectoralCreacion": 2103,
            "strJuradoElectoralCreacion": "MARISCAL NIETO",
            "intPosicion": 1,
            "idCargo": 16,
            "strCargo": "SENADOR",
            "strTipoDocumento": "DNI-E",
            "strDocumentoIdentidad": "04433822",
            "strNombres": "EDUARDO",
            "strApellidoPaterno": "SALAZAR",
            "strApellidoMaterno": "PEÑALOZA",
            "strSexo": "MASCULINO",
            "strFechaNacimiento": "5/01/1968 00:00:00",
            "strEsNativo": "NO",
            "strEstadoCandidato": "INSCRITO",
            "strGuidFoto": "d3b7f1a9-2c5a-4f80-990c-668bd23620a7",
            "strNombre": "d3b7f1a9-2c5a-4f80-990c-668bd23620a7.jpeg",
            "strUrlOrganizacionPolitica": "",
            "strCodExpedienteExt": "EG.2026016859",
            "idProcesoElectoral": 124,
            "strProcesoElectoral": "ELECCIONES GENERALES 2026",
            "idTipoEleccion": 21,
            "strTipoEleccion": "SENADORES DISTRITO MÚLTIPLE",
            "strAmbito": "NACIONAL",
            "strAnio_Eleccion": "2026",
            "strUbigeo": "170000",
            "strDepartamento": "MOQUEGUA",
            "strProvincia": ""
        },
        {
            "strDistrito": "",
            "idtipoorgpolitica": 1,
            "strTipoOrgPolitica": "PARTIDOS POLITICOS",
            "idOrganizacionPolitica": 2932,
            "strOrganizacionPolitica": "PARTIDO POLITICO PERU ACCION",
            "idJuradoElectoralCreacion": 2103,
            "strJuradoElectoralCreacion": "MARISCAL NIETO",
            "intPosicion": 1,
            "idCargo": 16,
            "strCargo": "SENADOR",
            "strTipoDocumento": "DNI",
            "strDocumentoIdentidad": "04725741",
            "strNombres": "ARTEMIO NEPTALI",
            "strApellidoPaterno": "FLORES",
            "strApellidoMaterno": "VENTURA",
            "strSexo": "MASCULINO",
            "strFechaNacimiento": "6/06/1968 00:00:00",
            "strEsNativo": "NO",
            "strEstadoCandidato": "IMPROCEDENTE",
            "strGuidFoto": "c5ea6458-4b31-42a4-84b6-0bdcd46a4f22",
            "strNombre": "c5ea6458-4b31-42a4-84b6-0bdcd46a4f22.jpg",
            "strUrlOrganizacionPolitica": "",
            "strCodExpedienteExt": "EG.2026017139",
            "idProcesoElectoral": 124,
            "strProcesoElectoral": "ELECCIONES GENERALES 2026",
            "idTipoEleccion": 21,
            "strTipoEleccion": "SENADORES DISTRITO MÚLTIPLE",
            "strAmbito": "NACIONAL",
            "strAnio_Eleccion": "2026",
            "strUbigeo": "170000",
            "strDepartamento": "MOQUEGUA",
            "strProvincia": ""
        },
        {
            "strDistrito": "",
            "idtipoorgpolitica": 1,
            "strTipoOrgPolitica": "PARTIDOS POLITICOS",
            "idOrganizacionPolitica": 2932,
            "strOrganizacionPolitica": "PARTIDO POLITICO PERU ACCION",
            "idJuradoElectoralCreacion": 2103,
            "strJuradoElectoralCreacion": "MARISCAL NIETO",
            "intPosicion": 2,
            "idCargo": 16,
            "strCargo": "SENADOR",
            "strTipoDocumento": "DNI",
            "strDocumentoIdentidad": "04630946",
            "strNombres": "LUCRECIA NORA",
            "strApellidoPaterno": "MALDONADO",
            "strApellidoMaterno": "CUADROS",
            "strSexo": "FEMENINO",
            "strFechaNacimiento": "30/06/1951 00:00:00",
            "strEsNativo": "NO",
            "strEstadoCandidato": "IMPROCEDENTE",
            "strGuidFoto": "05bb7834-6e10-4c61-8876-2ecac17b75d9",
            "strNombre": "05bb7834-6e10-4c61-8876-2ecac17b75d9.jpg",
            "strUrlOrganizacionPolitica": "",
            "strCodExpedienteExt": "EG.2026017139",
            "idProcesoElectoral": 124,
            "strProcesoElectoral": "ELECCIONES GENERALES 2026",
            "idTipoEleccion": 21,
            "strTipoEleccion": "SENADORES DISTRITO MÚLTIPLE",
            "strAmbito": "NACIONAL",
            "strAnio_Eleccion": "2026",
            "strUbigeo": "170000",
            "strDepartamento": "MOQUEGUA",
            "strProvincia": ""
        },
        {
            "strDistrito": "",
            "idtipoorgpolitica": 1,
            "strTipoOrgPolitica": "PARTIDOS POLITICOS",
            "idOrganizacionPolitica": 2925,
            "strOrganizacionPolitica": "PARTIDO POLITICO PERU PRIMERO",
            "idJuradoElectoralCreacion": 2103,
            "strJuradoElectoralCreacion": "MARISCAL NIETO",
            "intPosicion": 1,
            "idCargo": 16,
            "strCargo": "SENADOR",
            "strTipoDocumento": "DNI",
            "strDocumentoIdentidad": "04721719",
            "strNombres": "GRETHEL OLIVIA",
            "strApellidoPaterno": "CALLO",
            "strApellidoMaterno": "PAYE",
            "strSexo": "FEMENINO",
            "strFechaNacimiento": "24/02/1971 00:00:00",
            "strEsNativo": "NO",
            "strEstadoCandidato": "INSCRITO",
            "strGuidFoto": "0121547b-0c16-4f81-a976-355f6c451eb8",
            "strNombre": "0121547b-0c16-4f81-a976-355f6c451eb8.jpg",
            "strUrlOrganizacionPolitica": "",
            "strCodExpedienteExt": "EG.2026016949",
            "idProcesoElectoral": 124,
            "strProcesoElectoral": "ELECCIONES GENERALES 2026",
            "idTipoEleccion": 21,
            "strTipoEleccion": "SENADORES DISTRITO MÚLTIPLE",
            "strAmbito": "NACIONAL",
            "strAnio_Eleccion": "2026",
            "strUbigeo": "170000",
            "strDepartamento": "MOQUEGUA",
            "strProvincia": ""
        },
        {
            "strDistrito": "",
            "idtipoorgpolitica": 1,
            "strTipoOrgPolitica": "PARTIDOS POLITICOS",
            "idOrganizacionPolitica": 2925,
            "strOrganizacionPolitica": "PARTIDO POLITICO PERU PRIMERO",
            "idJuradoElectoralCreacion": 2103,
            "strJuradoElectoralCreacion": "MARISCAL NIETO",
            "intPosicion": 2,
            "idCargo": 16,
            "strCargo": "SENADOR",
            "strTipoDocumento": "DNI-E",
            "strDocumentoIdentidad": "04743805",
            "strNombres": "JAVIER DOLORES",
            "strApellidoPaterno": "ROMERO",
            "strApellidoMaterno": "LUNA",
            "strSexo": "MASCULINO",
            "strFechaNacimiento": "16/04/1958 00:00:00",
            "strEsNativo": "NO",
            "strEstadoCandidato": "INSCRITO",
            "strGuidFoto": "7a0890f7-3763-4144-86e8-e26a1e5d139f",
            "strNombre": "7a0890f7-3763-4144-86e8-e26a1e5d139f.jpg",
            "strUrlOrganizacionPolitica": "",
            "strCodExpedienteExt": "EG.2026016949",
            "idProcesoElectoral": 124,
            "strProcesoElectoral": "ELECCIONES GENERALES 2026",
            "idTipoEleccion": 21,
            "strTipoEleccion": "SENADORES DISTRITO MÚLTIPLE",
            "strAmbito": "NACIONAL",
            "strAnio_Eleccion": "2026",
            "strUbigeo": "170000",
            "strDepartamento": "MOQUEGUA",
            "strProvincia": ""
        },
        {
            "strDistrito": "",
            "idtipoorgpolitica": 1,
            "strTipoOrgPolitica": "PARTIDOS POLITICOS",
            "idOrganizacionPolitica": 2924,
            "strOrganizacionPolitica": "PERU MODERNO",
            "idJuradoElectoralCreacion": 2103,
            "strJuradoElectoralCreacion": "MARISCAL NIETO",
            "intPosicion": 1,
            "idCargo": 16,
            "strCargo": "SENADOR",
            "strTipoDocumento": "DNI",
            "strDocumentoIdentidad": "04415842",
            "strNombres": "MARCELINO",
            "strApellidoPaterno": "TITO",
            "strApellidoMaterno": "VALERIANO",
            "strSexo": "MASCULINO",
            "strFechaNacimiento": "16/01/1965 00:00:00",
            "strEsNativo": "NO",
            "strEstadoCandidato": "IMPROCEDENTE",
            "strGuidFoto": "ba108378-994a-48f6-be08-5593aa8bd92c",
            "strNombre": "ba108378-994a-48f6-be08-5593aa8bd92c.jpg",
            "strUrlOrganizacionPolitica": "",
            "strCodExpedienteExt": "EG.2026016932",
            "idProcesoElectoral": 124,
            "strProcesoElectoral": "ELECCIONES GENERALES 2026",
            "idTipoEleccion": 21,
            "strTipoEleccion": "SENADORES DISTRITO MÚLTIPLE",
            "strAmbito": "NACIONAL",
            "strAnio_Eleccion": "2026",
            "strUbigeo": "170000",
            "strDepartamento": "MOQUEGUA",
            "strProvincia": ""
        },
        {
            "strDistrito": "",
            "idtipoorgpolitica": 1,
            "strTipoOrgPolitica": "PARTIDOS POLITICOS",
            "idOrganizacionPolitica": 2924,
            "strOrganizacionPolitica": "PERU MODERNO",
            "idJuradoElectoralCreacion": 2103,
            "strJuradoElectoralCreacion": "MARISCAL NIETO",
            "intPosicion": 2,
            "idCargo": 16,
            "strCargo": "SENADOR",
            "strTipoDocumento": "DNI",
            "strDocumentoIdentidad": "04636858",
            "strNombres": "SONIA LIDIA",
            "strApellidoPaterno": "CONDORI",
            "strApellidoMaterno": "CONDORI",
            "strSexo": "FEMENINO",
            "strFechaNacimiento": "18/06/1968 00:00:00",
            "strEsNativo": "NO",
            "strEstadoCandidato": "INSCRITO",
            "strGuidFoto": "6d2c56ee-aae7-4b6c-85a0-b24894fe3f4d",
            "strNombre": "6d2c56ee-aae7-4b6c-85a0-b24894fe3f4d.jpg",
            "strUrlOrganizacionPolitica": "",
            "strCodExpedienteExt": "EG.2026016932",
            "idProcesoElectoral": 124,
            "strProcesoElectoral": "ELECCIONES GENERALES 2026",
            "idTipoEleccion": 21,
            "strTipoEleccion": "SENADORES DISTRITO MÚLTIPLE",
            "strAmbito": "NACIONAL",
            "strAnio_Eleccion": "2026",
            "strUbigeo": "170000",
            "strDepartamento": "MOQUEGUA",
            "strProvincia": ""
        },
        {
            "strDistrito": "",
            "idtipoorgpolitica": 1,
            "strTipoOrgPolitica": "PARTIDOS POLITICOS",
            "idOrganizacionPolitica": 2931,
            "strOrganizacionPolitica": "PRIMERO LA GENTE - COMUNIDAD, ECOLOGIA, LIBERTAD Y PROGRESO",
            "idJuradoElectoralCreacion": 2103,
            "strJuradoElectoralCreacion": "MARISCAL NIETO",
            "intPosicion": 2,
            "idCargo": 16,
            "strCargo": "SENADOR",
            "strTipoDocumento": "DNI",
            "strDocumentoIdentidad": "29568194",
            "strNombres": "MARIA SANDRA",
            "strApellidoPaterno": "SILVA",
            "strApellidoMaterno": "TORRES",
            "strSexo": "FEMENINO",
            "strFechaNacimiento": "8/09/1971 00:00:00",
            "strEsNativo": "NO",
            "strEstadoCandidato": "IMPROCEDENTE",
            "strGuidFoto": "66415f3b-17d8-4f9c-ad5d-5c215163c69f",
            "strNombre": "66415f3b-17d8-4f9c-ad5d-5c215163c69f.jpg",
            "strUrlOrganizacionPolitica": "",
            "strCodExpedienteExt": "EG.2026020130",
            "idProcesoElectoral": 124,
            "strProcesoElectoral": "ELECCIONES GENERALES 2026",
            "idTipoEleccion": 21,
            "strTipoEleccion": "SENADORES DISTRITO MÚLTIPLE",
            "strAmbito": "NACIONAL",
            "strAnio_Eleccion": "2026",
            "strUbigeo": "170000",
            "strDepartamento": "MOQUEGUA",
            "strProvincia": ""
        },
        {
            "strDistrito": "",
            "idtipoorgpolitica": 1,
            "strTipoOrgPolitica": "PARTIDOS POLITICOS",
            "idOrganizacionPolitica": 2931,
            "strOrganizacionPolitica": "PRIMERO LA GENTE - COMUNIDAD, ECOLOGIA, LIBERTAD Y PROGRESO",
            "idJuradoElectoralCreacion": 2103,
            "strJuradoElectoralCreacion": "MARISCAL NIETO",
            "intPosicion": 1,
            "idCargo": 16,
            "strCargo": "SENADOR",
            "strTipoDocumento": "DNI",
            "strDocumentoIdentidad": "04402947",
            "strNombres": "SIXTO CELESTINO",
            "strApellidoPaterno": "SOTO",
            "strApellidoMaterno": "JUAREZ",
            "strSexo": "MASCULINO",
            "strFechaNacimiento": "6/04/1960 00:00:00",
            "strEsNativo": "NO",
            "strEstadoCandidato": "INSCRITO",
            "strGuidFoto": "95a3c8ca-26f3-421b-b4d5-25dae9975ded",
            "strNombre": "95a3c8ca-26f3-421b-b4d5-25dae9975ded.jpg",
            "strUrlOrganizacionPolitica": "",
            "strCodExpedienteExt": "EG.2026020130",
            "idProcesoElectoral": 124,
            "strProcesoElectoral": "ELECCIONES GENERALES 2026",
            "idTipoEleccion": 21,
            "strTipoEleccion": "SENADORES DISTRITO MÚLTIPLE",
            "strAmbito": "NACIONAL",
            "strAnio_Eleccion": "2026",
            "strUbigeo": "170000",
            "strDepartamento": "MOQUEGUA",
            "strProvincia": ""
        },
        {
            "strDistrito": "",
            "idtipoorgpolitica": 1,
            "strTipoOrgPolitica": "PARTIDOS POLITICOS",
            "idOrganizacionPolitica": 2731,
            "strOrganizacionPolitica": "PODEMOS PERU",
            "idJuradoElectoralCreacion": 2103,
            "strJuradoElectoralCreacion": "MARISCAL NIETO",
            "intPosicion": 2,
            "idCargo": 16,
            "strCargo": "SENADOR",
            "strTipoDocumento": "DNI",
            "strDocumentoIdentidad": "04649632",
            "strNombres": "LIDIA ANA",
            "strApellidoPaterno": "CUTIPA",
            "strApellidoMaterno": "QUISPE",
            "strSexo": "FEMENINO",
            "strFechaNacimiento": "16/07/1973 00:00:00",
            "strEsNativo": "NO",
            "strEstadoCandidato": "INSCRITO",
            "strGuidFoto": "b5dc8191-dea5-4dc9-8b8c-172aa11c2d38",
            "strNombre": "b5dc8191-dea5-4dc9-8b8c-172aa11c2d38.jpg",
            "strUrlOrganizacionPolitica": "",
            "strCodExpedienteExt": "EG.2026016480",
            "idProcesoElectoral": 124,
            "strProcesoElectoral": "ELECCIONES GENERALES 2026",
            "idTipoEleccion": 21,
            "strTipoEleccion": "SENADORES DISTRITO MÚLTIPLE",
            "strAmbito": "NACIONAL",
            "strAnio_Eleccion": "2026",
            "strUbigeo": "170000",
            "strDepartamento": "MOQUEGUA",
            "strProvincia": ""
        },
        {
            "strDistrito": "",
            "idtipoorgpolitica": 1,
            "strTipoOrgPolitica": "PARTIDOS POLITICOS",
            "idOrganizacionPolitica": 2731,
            "strOrganizacionPolitica": "PODEMOS PERU",
            "idJuradoElectoralCreacion": 2103,
            "strJuradoElectoralCreacion": "MARISCAL NIETO",
            "intPosicion": 1,
            "idCargo": 16,
            "strCargo": "SENADOR",
            "strTipoDocumento": "DNI",
            "strDocumentoIdentidad": "04744843",
            "strNombres": "GUERSY RAFAEL",
            "strApellidoPaterno": "ROSADO",
            "strApellidoMaterno": "VENTURA",
            "strSexo": "MASCULINO",
            "strFechaNacimiento": "26/12/1975 00:00:00",
            "strEsNativo": "NO",
            "strEstadoCandidato": "INSCRITO",
            "strGuidFoto": "0eafcb36-58ac-474a-b87c-4946867d72cb",
            "strNombre": "0eafcb36-58ac-474a-b87c-4946867d72cb.jpg",
            "strUrlOrganizacionPolitica": "",
            "strCodExpedienteExt": "EG.2026016480",
            "idProcesoElectoral": 124,
            "strProcesoElectoral": "ELECCIONES GENERALES 2026",
            "idTipoEleccion": 21,
            "strTipoEleccion": "SENADORES DISTRITO MÚLTIPLE",
            "strAmbito": "NACIONAL",
            "strAnio_Eleccion": "2026",
            "strUbigeo": "170000",
            "strDepartamento": "MOQUEGUA",
            "strProvincia": ""
        },
        {
            "strDistrito": "",
            "idtipoorgpolitica": 1,
            "strTipoOrgPolitica": "PARTIDOS POLITICOS",
            "idOrganizacionPolitica": 2901,
            "strOrganizacionPolitica": "FRENTE POPULAR AGRICOLA FIA DEL PERU",
            "idJuradoElectoralCreacion": 2103,
            "strJuradoElectoralCreacion": "MARISCAL NIETO",
            "intPosicion": 1,
            "idCargo": 16,
            "strCargo": "SENADOR",
            "strTipoDocumento": "DNI-E",
            "strDocumentoIdentidad": "01546619",
            "strNombres": "LYLIAN LISBET",
            "strApellidoPaterno": "QUISPE",
            "strApellidoMaterno": "CONDORI",
            "strSexo": "FEMENINO",
            "strFechaNacimiento": "15/12/1974 00:00:00",
            "strEsNativo": "NO",
            "strEstadoCandidato": "INSCRITO",
            "strGuidFoto": "214c88ba-82e8-4cc4-9a6f-e1e5e5b2b91e",
            "strNombre": "214c88ba-82e8-4cc4-9a6f-e1e5e5b2b91e.jpg",
            "strUrlOrganizacionPolitica": "",
            "strCodExpedienteExt": "EG.2026015985",
            "idProcesoElectoral": 124,
            "strProcesoElectoral": "ELECCIONES GENERALES 2026",
            "idTipoEleccion": 21,
            "strTipoEleccion": "SENADORES DISTRITO MÚLTIPLE",
            "strAmbito": "NACIONAL",
            "strAnio_Eleccion": "2026",
            "strUbigeo": "170000",
            "strDepartamento": "MOQUEGUA",
            "strProvincia": ""
        },
        {
            "strDistrito": "",
            "idtipoorgpolitica": 1,
            "strTipoOrgPolitica": "PARTIDOS POLITICOS",
            "idOrganizacionPolitica": 2901,
            "strOrganizacionPolitica": "FRENTE POPULAR AGRICOLA FIA DEL PERU",
            "idJuradoElectoralCreacion": 2103,
            "strJuradoElectoralCreacion": "MARISCAL NIETO",
            "intPosicion": 2,
            "idCargo": 16,
            "strCargo": "SENADOR",
            "strTipoDocumento": "DNI",
            "strDocumentoIdentidad": "04749313",
            "strNombres": "JUAN DANIEL",
            "strApellidoPaterno": "VALDIVIA",
            "strApellidoMaterno": "GUERREROS",
            "strSexo": "MASCULINO",
            "strFechaNacimiento": "8/02/1977 00:00:00",
            "strEsNativo": "NO",
            "strEstadoCandidato": "INSCRITO",
            "strGuidFoto": "4e5a79d2-2db6-4bfe-8cf1-ccb1637e72a2",
            "strNombre": "4e5a79d2-2db6-4bfe-8cf1-ccb1637e72a2.jpg",
            "strUrlOrganizacionPolitica": "",
            "strCodExpedienteExt": "EG.2026015985",
            "idProcesoElectoral": 124,
            "strProcesoElectoral": "ELECCIONES GENERALES 2026",
            "idTipoEleccion": 21,
            "strTipoEleccion": "SENADORES DISTRITO MÚLTIPLE",
            "strAmbito": "NACIONAL",
            "strAnio_Eleccion": "2026",
            "strUbigeo": "170000",
            "strDepartamento": "MOQUEGUA",
            "strProvincia": ""
        },
        {
            "strDistrito": "",
            "idtipoorgpolitica": 1,
            "strTipoOrgPolitica": "PARTIDOS POLITICOS",
            "idOrganizacionPolitica": 2867,
            "strOrganizacionPolitica": "PARTIDO DEMOCRATA UNIDO PERU",
            "idJuradoElectoralCreacion": 2103,
            "strJuradoElectoralCreacion": "MARISCAL NIETO",
            "intPosicion": 2,
            "idCargo": 16,
            "strCargo": "SENADOR",
            "strTipoDocumento": "DNI",
            "strDocumentoIdentidad": "06995978",
            "strNombres": "MARCELIANO ROMAN",
            "strApellidoPaterno": "VEGA",
            "strApellidoMaterno": "ALMEYDA",
            "strSexo": "MASCULINO",
            "strFechaNacimiento": "9/08/1963 00:00:00",
            "strEsNativo": "NO",
            "strEstadoCandidato": "INSCRITO",
            "strGuidFoto": "d280ef77-b10e-4eb3-8d50-44deb6c019e1",
            "strNombre": "d280ef77-b10e-4eb3-8d50-44deb6c019e1.jpg",
            "strUrlOrganizacionPolitica": "",
            "strCodExpedienteExt": "EG.2026017449",
            "idProcesoElectoral": 124,
            "strProcesoElectoral": "ELECCIONES GENERALES 2026",
            "idTipoEleccion": 21,
            "strTipoEleccion": "SENADORES DISTRITO MÚLTIPLE",
            "strAmbito": "NACIONAL",
            "strAnio_Eleccion": "2026",
            "strUbigeo": "170000",
            "strDepartamento": "MOQUEGUA",
            "strProvincia": ""
        },
        {
            "strDistrito": "",
            "idtipoorgpolitica": 1,
            "strTipoOrgPolitica": "PARTIDOS POLITICOS",
            "idOrganizacionPolitica": 2895,
            "strOrganizacionPolitica": "PARTIDO DEMOCRATA VERDE",
            "idJuradoElectoralCreacion": 2103,
            "strJuradoElectoralCreacion": "MARISCAL NIETO",
            "intPosicion": 2,
            "idCargo": 16,
            "strCargo": "SENADOR",
            "strTipoDocumento": "DNI",
            "strDocumentoIdentidad": "16740408",
            "strNombres": "MAGALI",
            "strApellidoPaterno": "BENITES",
            "strApellidoMaterno": "CHAPOÑAN",
            "strSexo": "FEMENINO",
            "strFechaNacimiento": "29/05/1974 00:00:00",
            "strEsNativo": "NO",
            "strEstadoCandidato": "INSCRITO",
            "strGuidFoto": "c5efd58d-d28a-476c-a3ad-b1c5ed161c9d",
            "strNombre": "c5efd58d-d28a-476c-a3ad-b1c5ed161c9d.jpg",
            "strUrlOrganizacionPolitica": "",
            "strCodExpedienteExt": "EG.2026015531",
            "idProcesoElectoral": 124,
            "strProcesoElectoral": "ELECCIONES GENERALES 2026",
            "idTipoEleccion": 21,
            "strTipoEleccion": "SENADORES DISTRITO MÚLTIPLE",
            "strAmbito": "NACIONAL",
            "strAnio_Eleccion": "2026",
            "strUbigeo": "170000",
            "strDepartamento": "MOQUEGUA",
            "strProvincia": ""
        },
        {
            "strDistrito": "",
            "idtipoorgpolitica": 1,
            "strTipoOrgPolitica": "PARTIDOS POLITICOS",
            "idOrganizacionPolitica": 2895,
            "strOrganizacionPolitica": "PARTIDO DEMOCRATA VERDE",
            "idJuradoElectoralCreacion": 2103,
            "strJuradoElectoralCreacion": "MARISCAL NIETO",
            "intPosicion": 1,
            "idCargo": 16,
            "strCargo": "SENADOR",
            "strTipoDocumento": "DNI",
            "strDocumentoIdentidad": "10779813",
            "strNombres": "JOSE ABEL",
            "strApellidoPaterno": "VILCHEZ",
            "strApellidoMaterno": "VILCHEZ",
            "strSexo": "MASCULINO",
            "strFechaNacimiento": "17/07/1977 00:00:00",
            "strEsNativo": "NO",
            "strEstadoCandidato": "INSCRITO",
            "strGuidFoto": "4ddc6352-c496-4674-b1ca-a1f88e2617ba",
            "strNombre": "4ddc6352-c496-4674-b1ca-a1f88e2617ba.jpg",
            "strUrlOrganizacionPolitica": "",
            "strCodExpedienteExt": "EG.2026015531",
            "idProcesoElectoral": 124,
            "strProcesoElectoral": "ELECCIONES GENERALES 2026",
            "idTipoEleccion": 21,
            "strTipoEleccion": "SENADORES DISTRITO MÚLTIPLE",
            "strAmbito": "NACIONAL",
            "strAnio_Eleccion": "2026",
            "strUbigeo": "170000",
            "strDepartamento": "MOQUEGUA",
            "strProvincia": ""
        },
        {
            "strDistrito": "",
            "idtipoorgpolitica": 1,
            "strTipoOrgPolitica": "PARTIDOS POLITICOS",
            "idOrganizacionPolitica": 2985,
            "strOrganizacionPolitica": "PARTIDO POLITICO INTEGRIDAD DEMOCRATICA",
            "idJuradoElectoralCreacion": 2103,
            "strJuradoElectoralCreacion": "MARISCAL NIETO",
            "intPosicion": 2,
            "idCargo": 16,
            "strCargo": "SENADOR",
            "strTipoDocumento": "DNI",
            "strDocumentoIdentidad": "10307175",
            "strNombres": "NELI MARIT",
            "strApellidoPaterno": "LEON",
            "strApellidoMaterno": "DIAZ DE MASÍAS",
            "strSexo": "FEMENINO",
            "strFechaNacimiento": "16/11/1966 00:00:00",
            "strEsNativo": "NO",
            "strEstadoCandidato": "INSCRITO",
            "strGuidFoto": "60cc553e-6540-4600-9fd3-af97e7aad851",
            "strNombre": "60cc553e-6540-4600-9fd3-af97e7aad851.jpg",
            "strUrlOrganizacionPolitica": "",
            "strCodExpedienteExt": "EG.2026017373",
            "idProcesoElectoral": 124,
            "strProcesoElectoral": "ELECCIONES GENERALES 2026",
            "idTipoEleccion": 21,
            "strTipoEleccion": "SENADORES DISTRITO MÚLTIPLE",
            "strAmbito": "NACIONAL",
            "strAnio_Eleccion": "2026",
            "strUbigeo": "170000",
            "strDepartamento": "MOQUEGUA",
            "strProvincia": ""
        },
        {
            "strDistrito": "",
            "idtipoorgpolitica": 1,
            "strTipoOrgPolitica": "PARTIDOS POLITICOS",
            "idOrganizacionPolitica": 2985,
            "strOrganizacionPolitica": "PARTIDO POLITICO INTEGRIDAD DEMOCRATICA",
            "idJuradoElectoralCreacion": 2103,
            "strJuradoElectoralCreacion": "MARISCAL NIETO",
            "intPosicion": 1,
            "idCargo": 16,
            "strCargo": "SENADOR",
            "strTipoDocumento": "DNI",
            "strDocumentoIdentidad": "06989424",
            "strNombres": "JOHNNY DANTE",
            "strApellidoPaterno": "PRETELL",
            "strApellidoMaterno": "FRANCIA",
            "strSexo": "MASCULINO",
            "strFechaNacimiento": "22/06/1965 00:00:00",
            "strEsNativo": "NO",
            "strEstadoCandidato": "INSCRITO",
            "strGuidFoto": "5c32c5ea-d534-4d64-a8f3-8676c97cd711",
            "strNombre": "5c32c5ea-d534-4d64-a8f3-8676c97cd711.jpg",
            "strUrlOrganizacionPolitica": "",
            "strCodExpedienteExt": "EG.2026017373",
            "idProcesoElectoral": 124,
            "strProcesoElectoral": "ELECCIONES GENERALES 2026",
            "idTipoEleccion": 21,
            "strTipoEleccion": "SENADORES DISTRITO MÚLTIPLE",
            "strAmbito": "NACIONAL",
            "strAnio_Eleccion": "2026",
            "strUbigeo": "170000",
            "strDepartamento": "MOQUEGUA",
            "strProvincia": ""
        },
        {
            "strDistrito": "",
            "idtipoorgpolitica": 1,
            "strTipoOrgPolitica": "PARTIDOS POLITICOS",
            "idOrganizacionPolitica": 2998,
            "strOrganizacionPolitica": "UN CAMINO DIFERENTE",
            "idJuradoElectoralCreacion": 2103,
            "strJuradoElectoralCreacion": "MARISCAL NIETO",
            "intPosicion": 2,
            "idCargo": 16,
            "strCargo": "SENADOR",
            "strTipoDocumento": "DNI",
            "strDocumentoIdentidad": "18083138",
            "strNombres": "RUBIN YOLANDA",
            "strApellidoPaterno": "REYES",
            "strApellidoMaterno": "QUIÑONES",
            "strSexo": "FEMENINO",
            "strFechaNacimiento": "11/06/1968 00:00:00",
            "strEsNativo": "NO",
            "strEstadoCandidato": "INSCRITO",
            "strGuidFoto": "b05e7316-fd2e-4193-b875-1ad09332d5dc",
            "strNombre": "b05e7316-fd2e-4193-b875-1ad09332d5dc.jpg",
            "strUrlOrganizacionPolitica": "",
            "strCodExpedienteExt": "EG.2026015845",
            "idProcesoElectoral": 124,
            "strProcesoElectoral": "ELECCIONES GENERALES 2026",
            "idTipoEleccion": 21,
            "strTipoEleccion": "SENADORES DISTRITO MÚLTIPLE",
            "strAmbito": "NACIONAL",
            "strAnio_Eleccion": "2026",
            "strUbigeo": "170000",
            "strDepartamento": "MOQUEGUA",
            "strProvincia": ""
        },
        {
            "strDistrito": "",
            "idtipoorgpolitica": 1,
            "strTipoOrgPolitica": "PARTIDOS POLITICOS",
            "idOrganizacionPolitica": 2998,
            "strOrganizacionPolitica": "UN CAMINO DIFERENTE",
            "idJuradoElectoralCreacion": 2103,
            "strJuradoElectoralCreacion": "MARISCAL NIETO",
            "intPosicion": 1,
            "idCargo": 16,
            "strCargo": "SENADOR",
            "strTipoDocumento": "DNI",
            "strDocumentoIdentidad": "40084096",
            "strNombres": "RENATTO GENARO",
            "strApellidoPaterno": "OTINIANO",
            "strApellidoMaterno": "ULLOA",
            "strSexo": "MASCULINO",
            "strFechaNacimiento": "6/09/1978 00:00:00",
            "strEsNativo": "NO",
            "strEstadoCandidato": "INSCRITO",
            "strGuidFoto": "9c23c774-9def-4e5b-875a-3492f5b32474",
            "strNombre": "9c23c774-9def-4e5b-875a-3492f5b32474.jpg",
            "strUrlOrganizacionPolitica": "",
            "strCodExpedienteExt": "EG.2026015845",
            "idProcesoElectoral": 124,
            "strProcesoElectoral": "ELECCIONES GENERALES 2026",
            "idTipoEleccion": 21,
            "strTipoEleccion": "SENADORES DISTRITO MÚLTIPLE",
            "strAmbito": "NACIONAL",
            "strAnio_Eleccion": "2026",
            "strUbigeo": "170000",
            "strDepartamento": "MOQUEGUA",
            "strProvincia": ""
        },
        {
            "strDistrito": "",
            "idtipoorgpolitica": 1,
            "strTipoOrgPolitica": "PARTIDOS POLITICOS",
            "idOrganizacionPolitica": 2980,
            "strOrganizacionPolitica": "AHORA NACION - AN",
            "idJuradoElectoralCreacion": 2103,
            "strJuradoElectoralCreacion": "MARISCAL NIETO",
            "intPosicion": 2,
            "idCargo": 16,
            "strCargo": "SENADOR",
            "strTipoDocumento": "DNI",
            "strDocumentoIdentidad": "30853982",
            "strNombres": "MARIA ELENA",
            "strApellidoPaterno": "CHOQUE",
            "strApellidoMaterno": "MAMANI",
            "strSexo": "FEMENINO",
            "strFechaNacimiento": "27/04/1969 00:00:00",
            "strEsNativo": "NO",
            "strEstadoCandidato": "INSCRITO",
            "strGuidFoto": "fe7f7937-f7e1-4da4-9158-8cd9167dda77",
            "strNombre": "fe7f7937-f7e1-4da4-9158-8cd9167dda77.jpg",
            "strUrlOrganizacionPolitica": "",
            "strCodExpedienteExt": "EG.2026016041",
            "idProcesoElectoral": 124,
            "strProcesoElectoral": "ELECCIONES GENERALES 2026",
            "idTipoEleccion": 21,
            "strTipoEleccion": "SENADORES DISTRITO MÚLTIPLE",
            "strAmbito": "NACIONAL",
            "strAnio_Eleccion": "2026",
            "strUbigeo": "170000",
            "strDepartamento": "MOQUEGUA",
            "strProvincia": ""
        },
        {
            "strDistrito": "",
            "idtipoorgpolitica": 1,
            "strTipoOrgPolitica": "PARTIDOS POLITICOS",
            "idOrganizacionPolitica": 2980,
            "strOrganizacionPolitica": "AHORA NACION - AN",
            "idJuradoElectoralCreacion": 2103,
            "strJuradoElectoralCreacion": "MARISCAL NIETO",
            "intPosicion": 1,
            "idCargo": 16,
            "strCargo": "SENADOR",
            "strTipoDocumento": "DNI",
            "strDocumentoIdentidad": "23993246",
            "strNombres": "MAGNO",
            "strApellidoPaterno": "QUISPE",
            "strApellidoMaterno": "FARFAN",
            "strSexo": "MASCULINO",
            "strFechaNacimiento": "27/05/1953 00:00:00",
            "strEsNativo": "NO",
            "strEstadoCandidato": "INSCRITO",
            "strGuidFoto": "647afe6a-4d4d-451b-8748-c9a5155337e1",
            "strNombre": "647afe6a-4d4d-451b-8748-c9a5155337e1.jpg",
            "strUrlOrganizacionPolitica": "",
            "strCodExpedienteExt": "EG.2026016041",
            "idProcesoElectoral": 124,
            "strProcesoElectoral": "ELECCIONES GENERALES 2026",
            "idTipoEleccion": 21,
            "strTipoEleccion": "SENADORES DISTRITO MÚLTIPLE",
            "strAmbito": "NACIONAL",
            "strAnio_Eleccion": "2026",
            "strUbigeo": "170000",
            "strDepartamento": "MOQUEGUA",
            "strProvincia": ""
        },
        {
            "strDistrito": "",
            "idtipoorgpolitica": 1,
            "strTipoOrgPolitica": "PARTIDOS POLITICOS",
            "idOrganizacionPolitica": 2961,
            "strOrganizacionPolitica": "PARTIDO DEL BUEN GOBIERNO",
            "idJuradoElectoralCreacion": 2103,
            "strJuradoElectoralCreacion": "MARISCAL NIETO",
            "intPosicion": 2,
            "idCargo": 16,
            "strCargo": "SENADOR",
            "strTipoDocumento": "DNI",
            "strDocumentoIdentidad": "04646017",
            "strNombres": "LILIANA GLORIA",
            "strApellidoPaterno": "FERNANDEZ",
            "strApellidoMaterno": "NINA",
            "strSexo": "FEMENINO",
            "strFechaNacimiento": "10/04/1971 00:00:00",
            "strEsNativo": "NO",
            "strEstadoCandidato": "INSCRITO",
            "strGuidFoto": "6455d1c4-8479-4e74-a1ce-834b0a8bd505",
            "strNombre": "6455d1c4-8479-4e74-a1ce-834b0a8bd505.jpg",
            "strUrlOrganizacionPolitica": "",
            "strCodExpedienteExt": "EG.2026016152",
            "idProcesoElectoral": 124,
            "strProcesoElectoral": "ELECCIONES GENERALES 2026",
            "idTipoEleccion": 21,
            "strTipoEleccion": "SENADORES DISTRITO MÚLTIPLE",
            "strAmbito": "NACIONAL",
            "strAnio_Eleccion": "2026",
            "strUbigeo": "170000",
            "strDepartamento": "MOQUEGUA",
            "strProvincia": ""
        },
        {
            "strDistrito": "",
            "idtipoorgpolitica": 1,
            "strTipoOrgPolitica": "PARTIDOS POLITICOS",
            "idOrganizacionPolitica": 2986,
            "strOrganizacionPolitica": "PARTIDO DEMOCRATICO FEDERAL",
            "idJuradoElectoralCreacion": 2103,
            "strJuradoElectoralCreacion": "MARISCAL NIETO",
            "intPosicion": 1,
            "idCargo": 16,
            "strCargo": "SENADOR",
            "strTipoDocumento": "DNI",
            "strDocumentoIdentidad": "09869347",
            "strNombres": "MIGUEL",
            "strApellidoPaterno": "RUIZ",
            "strApellidoMaterno": "PEÑA",
            "strSexo": "MASCULINO",
            "strFechaNacimiento": "23/07/1972 00:00:00",
            "strEsNativo": "NO",
            "strEstadoCandidato": "IMPROCEDENTE",
            "strGuidFoto": "4baec8a6-b495-4871-8e6a-0b5cf64491b1",
            "strNombre": "4baec8a6-b495-4871-8e6a-0b5cf64491b1.jpg",
            "strUrlOrganizacionPolitica": "",
            "strCodExpedienteExt": "EG.2026016692",
            "idProcesoElectoral": 124,
            "strProcesoElectoral": "ELECCIONES GENERALES 2026",
            "idTipoEleccion": 21,
            "strTipoEleccion": "SENADORES DISTRITO MÚLTIPLE",
            "strAmbito": "NACIONAL",
            "strAnio_Eleccion": "2026",
            "strUbigeo": "170000",
            "strDepartamento": "MOQUEGUA",
            "strProvincia": ""
        },
        {
            "strDistrito": "",
            "idtipoorgpolitica": 1,
            "strTipoOrgPolitica": "PARTIDOS POLITICOS",
            "idOrganizacionPolitica": 2986,
            "strOrganizacionPolitica": "PARTIDO DEMOCRATICO FEDERAL",
            "idJuradoElectoralCreacion": 2103,
            "strJuradoElectoralCreacion": "MARISCAL NIETO",
            "intPosicion": 2,
            "idCargo": 16,
            "strCargo": "SENADOR",
            "strTipoDocumento": "DNI",
            "strDocumentoIdentidad": "04632607",
            "strNombres": "GLADYS FERMINA",
            "strApellidoPaterno": "ROJAS",
            "strApellidoMaterno": "DE VALERIO",
            "strSexo": "FEMENINO",
            "strFechaNacimiento": "7/07/1958 00:00:00",
            "strEsNativo": "NO",
            "strEstadoCandidato": "IMPROCEDENTE",
            "strGuidFoto": "1d550a00-a303-4fe2-8a1b-83499309d4d2",
            "strNombre": "1d550a00-a303-4fe2-8a1b-83499309d4d2.jpg",
            "strUrlOrganizacionPolitica": "",
            "strCodExpedienteExt": "EG.2026016692",
            "idProcesoElectoral": 124,
            "strProcesoElectoral": "ELECCIONES GENERALES 2026",
            "idTipoEleccion": 21,
            "strTipoEleccion": "SENADORES DISTRITO MÚLTIPLE",
            "strAmbito": "NACIONAL",
            "strAnio_Eleccion": "2026",
            "strUbigeo": "170000",
            "strDepartamento": "MOQUEGUA",
            "strProvincia": ""
        },
        {
            "strDistrito": "",
            "idtipoorgpolitica": 1,
            "strTipoOrgPolitica": "PARTIDOS POLITICOS",
            "idOrganizacionPolitica": 2956,
            "strOrganizacionPolitica": "PARTIDO PAIS PARA TODOS",
            "idJuradoElectoralCreacion": 2103,
            "strJuradoElectoralCreacion": "MARISCAL NIETO",
            "intPosicion": 1,
            "idCargo": 16,
            "strCargo": "SENADOR",
            "strTipoDocumento": "DNI",
            "strDocumentoIdentidad": "03870630",
            "strNombres": "JOSE LUIS ESTEBAN",
            "strApellidoPaterno": "CRUZ",
            "strApellidoMaterno": "MOGOLLON",
            "strSexo": "MASCULINO",
            "strFechaNacimiento": "10/03/1976 00:00:00",
            "strEsNativo": "NO",
            "strEstadoCandidato": "INSCRITO",
            "strGuidFoto": "3bae8fc7-5ae9-4f9b-95a7-de01e61915d1",
            "strNombre": "3bae8fc7-5ae9-4f9b-95a7-de01e61915d1.jpg",
            "strUrlOrganizacionPolitica": "",
            "strCodExpedienteExt": "EG.2026016816",
            "idProcesoElectoral": 124,
            "strProcesoElectoral": "ELECCIONES GENERALES 2026",
            "idTipoEleccion": 21,
            "strTipoEleccion": "SENADORES DISTRITO MÚLTIPLE",
            "strAmbito": "NACIONAL",
            "strAnio_Eleccion": "2026",
            "strUbigeo": "170000",
            "strDepartamento": "MOQUEGUA",
            "strProvincia": ""
        },
        {
            "strDistrito": "",
            "idtipoorgpolitica": 1,
            "strTipoOrgPolitica": "PARTIDOS POLITICOS",
            "idOrganizacionPolitica": 2956,
            "strOrganizacionPolitica": "PARTIDO PAIS PARA TODOS",
            "idJuradoElectoralCreacion": 2103,
            "strJuradoElectoralCreacion": "MARISCAL NIETO",
            "intPosicion": 2,
            "idCargo": 16,
            "strCargo": "SENADOR",
            "strTipoDocumento": "DNI",
            "strDocumentoIdentidad": "07518649",
            "strNombres": "MARIELA ISABET",
            "strApellidoPaterno": "OSCCO",
            "strApellidoMaterno": "VASQUEZ",
            "strSexo": "FEMENINO",
            "strFechaNacimiento": "27/10/1973 00:00:00",
            "strEsNativo": "NO",
            "strEstadoCandidato": "INSCRITO",
            "strGuidFoto": "15edb316-d02e-401e-9cfe-50115e4989ae",
            "strNombre": "15edb316-d02e-401e-9cfe-50115e4989ae.jpg",
            "strUrlOrganizacionPolitica": "",
            "strCodExpedienteExt": "EG.2026016816",
            "idProcesoElectoral": 124,
            "strProcesoElectoral": "ELECCIONES GENERALES 2026",
            "idTipoEleccion": 21,
            "strTipoEleccion": "SENADORES DISTRITO MÚLTIPLE",
            "strAmbito": "NACIONAL",
            "strAnio_Eleccion": "2026",
            "strUbigeo": "170000",
            "strDepartamento": "MOQUEGUA",
            "strProvincia": ""
        },
        {
            "strDistrito": "",
            "idtipoorgpolitica": 1,
            "strTipoOrgPolitica": "PARTIDOS POLITICOS",
            "idOrganizacionPolitica": 2995,
            "strOrganizacionPolitica": "PARTIDO POLITICO COOPERACION POPULAR",
            "idJuradoElectoralCreacion": 2103,
            "strJuradoElectoralCreacion": "MARISCAL NIETO",
            "intPosicion": 2,
            "idCargo": 16,
            "strCargo": "SENADOR",
            "strTipoDocumento": "DNI",
            "strDocumentoIdentidad": "10555690",
            "strNombres": "ANGELICA",
            "strApellidoPaterno": "TORRES",
            "strApellidoMaterno": "AMASIFUEN",
            "strSexo": "FEMENINO",
            "strFechaNacimiento": "3/03/1952 00:00:00",
            "strEsNativo": "NO",
            "strEstadoCandidato": "INSCRITO",
            "strGuidFoto": "ba82e5b0-dff7-4351-abd6-3c41479363e4",
            "strNombre": "ba82e5b0-dff7-4351-abd6-3c41479363e4.jpg",
            "strUrlOrganizacionPolitica": "",
            "strCodExpedienteExt": "EG.2026017002",
            "idProcesoElectoral": 124,
            "strProcesoElectoral": "ELECCIONES GENERALES 2026",
            "idTipoEleccion": 21,
            "strTipoEleccion": "SENADORES DISTRITO MÚLTIPLE",
            "strAmbito": "NACIONAL",
            "strAnio_Eleccion": "2026",
            "strUbigeo": "170000",
            "strDepartamento": "MOQUEGUA",
            "strProvincia": ""
        },
        {
            "strDistrito": "",
            "idtipoorgpolitica": 1,
            "strTipoOrgPolitica": "PARTIDOS POLITICOS",
            "idOrganizacionPolitica": 2995,
            "strOrganizacionPolitica": "PARTIDO POLITICO COOPERACION POPULAR",
            "idJuradoElectoralCreacion": 2103,
            "strJuradoElectoralCreacion": "MARISCAL NIETO",
            "intPosicion": 1,
            "idCargo": 16,
            "strCargo": "SENADOR",
            "strTipoDocumento": "DNI",
            "strDocumentoIdentidad": "10318840",
            "strNombres": "FREDDY",
            "strApellidoPaterno": "SALAZAR",
            "strApellidoMaterno": "LEGUIA",
            "strSexo": "MASCULINO",
            "strFechaNacimiento": "31/03/1976 00:00:00",
            "strEsNativo": "NO",
            "strEstadoCandidato": "INSCRITO",
            "strGuidFoto": "8a8beb29-a418-42eb-9c47-073adcaf11f6",
            "strNombre": "8a8beb29-a418-42eb-9c47-073adcaf11f6.jpg",
            "strUrlOrganizacionPolitica": "",
            "strCodExpedienteExt": "EG.2026017002",
            "idProcesoElectoral": 124,
            "strProcesoElectoral": "ELECCIONES GENERALES 2026",
            "idTipoEleccion": 21,
            "strTipoEleccion": "SENADORES DISTRITO MÚLTIPLE",
            "strAmbito": "NACIONAL",
            "strAnio_Eleccion": "2026",
            "strUbigeo": "170000",
            "strDepartamento": "MOQUEGUA",
            "strProvincia": ""
        },
        {
            "strDistrito": "",
            "idtipoorgpolitica": 1,
            "strTipoOrgPolitica": "PARTIDOS POLITICOS",
            "idOrganizacionPolitica": 2967,
            "strOrganizacionPolitica": "PROGRESEMOS",
            "idJuradoElectoralCreacion": 2103,
            "strJuradoElectoralCreacion": "MARISCAL NIETO",
            "intPosicion": 1,
            "idCargo": 16,
            "strCargo": "SENADOR",
            "strTipoDocumento": "DNI-E",
            "strDocumentoIdentidad": "09630996",
            "strNombres": "NICOLAS",
            "strApellidoPaterno": "SAENZ",
            "strApellidoMaterno": "PASCUAL",
            "strSexo": "MASCULINO",
            "strFechaNacimiento": "9/05/1960 00:00:00",
            "strEsNativo": "NO",
            "strEstadoCandidato": "INSCRITO",
            "strGuidFoto": "2616f476-c278-4748-aef1-6e35a6bccbb7",
            "strNombre": "2616f476-c278-4748-aef1-6e35a6bccbb7.jpg",
            "strUrlOrganizacionPolitica": "",
            "strCodExpedienteExt": "EG.2026017412",
            "idProcesoElectoral": 124,
            "strProcesoElectoral": "ELECCIONES GENERALES 2026",
            "idTipoEleccion": 21,
            "strTipoEleccion": "SENADORES DISTRITO MÚLTIPLE",
            "strAmbito": "NACIONAL",
            "strAnio_Eleccion": "2026",
            "strUbigeo": "170000",
            "strDepartamento": "MOQUEGUA",
            "strProvincia": ""
        },
        {
            "strDistrito": "",
            "idtipoorgpolitica": 1,
            "strTipoOrgPolitica": "PARTIDOS POLITICOS",
            "idOrganizacionPolitica": 2967,
            "strOrganizacionPolitica": "PROGRESEMOS",
            "idJuradoElectoralCreacion": 2103,
            "strJuradoElectoralCreacion": "MARISCAL NIETO",
            "intPosicion": 2,
            "idCargo": 16,
            "strCargo": "SENADOR",
            "strTipoDocumento": "DNI",
            "strDocumentoIdentidad": "04437137",
            "strNombres": "OLGA LIDIA",
            "strApellidoPaterno": "LOPEZ",
            "strApellidoMaterno": "CAUNA",
            "strSexo": "FEMENINO",
            "strFechaNacimiento": "4/04/1974 00:00:00",
            "strEsNativo": "NO",
            "strEstadoCandidato": "INSCRITO",
            "strGuidFoto": "c2e16682-d696-42ce-8cf6-864b0ab0c70b",
            "strNombre": "c2e16682-d696-42ce-8cf6-864b0ab0c70b.jpg",
            "strUrlOrganizacionPolitica": "",
            "strCodExpedienteExt": "EG.2026017412",
            "idProcesoElectoral": 124,
            "strProcesoElectoral": "ELECCIONES GENERALES 2026",
            "idTipoEleccion": 21,
            "strTipoEleccion": "SENADORES DISTRITO MÚLTIPLE",
            "strAmbito": "NACIONAL",
            "strAnio_Eleccion": "2026",
            "strUbigeo": "170000",
            "strDepartamento": "MOQUEGUA",
            "strProvincia": ""
        },
        {
            "strDistrito": "",
            "idtipoorgpolitica": 1,
            "strTipoOrgPolitica": "PARTIDOS POLITICOS",
            "idOrganizacionPolitica": 2921,
            "strOrganizacionPolitica": "PARTIDO POLITICO PRIN",
            "idJuradoElectoralCreacion": 2103,
            "strJuradoElectoralCreacion": "MARISCAL NIETO",
            "intPosicion": 1,
            "idCargo": 16,
            "strCargo": "SENADOR",
            "strTipoDocumento": "DNI-E",
            "strDocumentoIdentidad": "04429992",
            "strNombres": "CARLOS ALBERTO",
            "strApellidoPaterno": "CALDERON",
            "strApellidoMaterno": "SALAS",
            "strSexo": "MASCULINO",
            "strFechaNacimiento": "18/03/1975 00:00:00",
            "strEsNativo": "NO",
            "strEstadoCandidato": "INSCRITO",
            "strGuidFoto": "2029fe7e-b32a-466e-82be-3573f906b60f",
            "strNombre": "2029fe7e-b32a-466e-82be-3573f906b60f.jpg",
            "strUrlOrganizacionPolitica": "",
            "strCodExpedienteExt": "EG.2026017267",
            "idProcesoElectoral": 124,
            "strProcesoElectoral": "ELECCIONES GENERALES 2026",
            "idTipoEleccion": 21,
            "strTipoEleccion": "SENADORES DISTRITO MÚLTIPLE",
            "strAmbito": "NACIONAL",
            "strAnio_Eleccion": "2026",
            "strUbigeo": "170000",
            "strDepartamento": "MOQUEGUA",
            "strProvincia": ""
        },
        {
            "strDistrito": "",
            "idtipoorgpolitica": 1,
            "strTipoOrgPolitica": "PARTIDOS POLITICOS",
            "idOrganizacionPolitica": 2921,
            "strOrganizacionPolitica": "PARTIDO POLITICO PRIN",
            "idJuradoElectoralCreacion": 2103,
            "strJuradoElectoralCreacion": "MARISCAL NIETO",
            "intPosicion": 2,
            "idCargo": 16,
            "strCargo": "SENADOR",
            "strTipoDocumento": "DNI",
            "strDocumentoIdentidad": "04416932",
            "strNombres": "MARIA INES",
            "strApellidoPaterno": "DANCE",
            "strApellidoMaterno": "PERALTA",
            "strSexo": "FEMENINO",
            "strFechaNacimiento": "19/12/1966 00:00:00",
            "strEsNativo": "NO",
            "strEstadoCandidato": "INSCRITO",
            "strGuidFoto": "c4cfec54-2268-47f5-bf6a-bca3411500ca",
            "strNombre": "c4cfec54-2268-47f5-bf6a-bca3411500ca.jpg",
            "strUrlOrganizacionPolitica": "",
            "strCodExpedienteExt": "EG.2026017267",
            "idProcesoElectoral": 124,
            "strProcesoElectoral": "ELECCIONES GENERALES 2026",
            "idTipoEleccion": 21,
            "strTipoEleccion": "SENADORES DISTRITO MÚLTIPLE",
            "strAmbito": "NACIONAL",
            "strAnio_Eleccion": "2026",
            "strUbigeo": "170000",
            "strDepartamento": "MOQUEGUA",
            "strProvincia": ""
        },
        {
            "strDistrito": "",
            "idtipoorgpolitica": 5,
            "strTipoOrgPolitica": "ALIANZAS ELECTORALES",
            "idOrganizacionPolitica": 3025,
            "strOrganizacionPolitica": "ALIANZA ELECTORAL VENCEREMOS",
            "idJuradoElectoralCreacion": 2103,
            "strJuradoElectoralCreacion": "MARISCAL NIETO",
            "intPosicion": 1,
            "idCargo": 16,
            "strCargo": "SENADOR",
            "strTipoDocumento": "DNI",
            "strDocumentoIdentidad": "04653597",
            "strNombres": "RUBEN GELBER",
            "strApellidoPaterno": "VELASQUEZ",
            "strApellidoMaterno": "RAMOS",
            "strSexo": "MASCULINO",
            "strFechaNacimiento": "28/09/1978 00:00:00",
            "strEsNativo": "NO",
            "strEstadoCandidato": "INSCRITO",
            "strGuidFoto": "f7c29804-6df0-4ea8-a530-2369ac86e479",
            "strNombre": "f7c29804-6df0-4ea8-a530-2369ac86e479.jpg",
            "strUrlOrganizacionPolitica": "",
            "strCodExpedienteExt": "EG.2026016540",
            "idProcesoElectoral": 124,
            "strProcesoElectoral": "ELECCIONES GENERALES 2026",
            "idTipoEleccion": 21,
            "strTipoEleccion": "SENADORES DISTRITO MÚLTIPLE",
            "strAmbito": "NACIONAL",
            "strAnio_Eleccion": "2026",
            "strUbigeo": "170000",
            "strDepartamento": "MOQUEGUA",
            "strProvincia": ""
        },
        {
            "strDistrito": "",
            "idtipoorgpolitica": 5,
            "strTipoOrgPolitica": "ALIANZAS ELECTORALES",
            "idOrganizacionPolitica": 3024,
            "strOrganizacionPolitica": "FUERZA Y LIBERTAD",
            "idJuradoElectoralCreacion": 2103,
            "strJuradoElectoralCreacion": "MARISCAL NIETO",
            "intPosicion": 1,
            "idCargo": 16,
            "strCargo": "SENADOR",
            "strTipoDocumento": "DNI",
            "strDocumentoIdentidad": "10273333",
            "strNombres": "UBEN ENRIQUE",
            "strApellidoPaterno": "ATOCHE",
            "strApellidoMaterno": "KONG",
            "strSexo": "MASCULINO",
            "strFechaNacimiento": "8/03/1965 00:00:00",
            "strEsNativo": "NO",
            "strEstadoCandidato": "APELACIÓN",
            "strGuidFoto": "87e97eda-b0a9-4ed2-a431-372a672cdb64",
            "strNombre": "87e97eda-b0a9-4ed2-a431-372a672cdb64.jpg",
            "strUrlOrganizacionPolitica": "",
            "strCodExpedienteExt": "EG.2026016311",
            "idProcesoElectoral": 124,
            "strProcesoElectoral": "ELECCIONES GENERALES 2026",
            "idTipoEleccion": 21,
            "strTipoEleccion": "SENADORES DISTRITO MÚLTIPLE",
            "strAmbito": "NACIONAL",
            "strAnio_Eleccion": "2026",
            "strUbigeo": "170000",
            "strDepartamento": "MOQUEGUA",
            "strProvincia": ""
        },
        {
            "strDistrito": "",
            "idtipoorgpolitica": 5,
            "strTipoOrgPolitica": "ALIANZAS ELECTORALES",
            "idOrganizacionPolitica": 3024,
            "strOrganizacionPolitica": "FUERZA Y LIBERTAD",
            "idJuradoElectoralCreacion": 2103,
            "strJuradoElectoralCreacion": "MARISCAL NIETO",
            "intPosicion": 2,
            "idCargo": 16,
            "strCargo": "SENADOR",
            "strTipoDocumento": "DNI",
            "strDocumentoIdentidad": "20658526",
            "strNombres": "GLADYS EVA",
            "strApellidoPaterno": "OSORIO",
            "strApellidoMaterno": "ESTEBAN",
            "strSexo": "FEMENINO",
            "strFechaNacimiento": "16/07/1968 00:00:00",
            "strEsNativo": "NO",
            "strEstadoCandidato": "INSCRITO",
            "strGuidFoto": "b7eb0361-3591-4ce6-aff5-fa395d2d4753",
            "strNombre": "b7eb0361-3591-4ce6-aff5-fa395d2d4753.jpg",
            "strUrlOrganizacionPolitica": "",
            "strCodExpedienteExt": "EG.2026016311",
            "idProcesoElectoral": 124,
            "strProcesoElectoral": "ELECCIONES GENERALES 2026",
            "idTipoEleccion": 21,
            "strTipoEleccion": "SENADORES DISTRITO MÚLTIPLE",
            "strAmbito": "NACIONAL",
            "strAnio_Eleccion": "2026",
            "strUbigeo": "170000",
            "strDepartamento": "MOQUEGUA",
            "strProvincia": ""
        },
        {
            "strDistrito": "",
            "idtipoorgpolitica": 5,
            "strTipoOrgPolitica": "ALIANZAS ELECTORALES",
            "idOrganizacionPolitica": 3023,
            "strOrganizacionPolitica": "UNIDAD NACIONAL",
            "idJuradoElectoralCreacion": 2103,
            "strJuradoElectoralCreacion": "MARISCAL NIETO",
            "intPosicion": 2,
            "idCargo": 16,
            "strCargo": "SENADOR",
            "strTipoDocumento": "DNI",
            "strDocumentoIdentidad": "04641352",
            "strNombres": "LIDIA MICHELI",
            "strApellidoPaterno": "POLO",
            "strApellidoMaterno": "CARDENAS",
            "strSexo": "FEMENINO",
            "strFechaNacimiento": "28/02/1970 00:00:00",
            "strEsNativo": "NO",
            "strEstadoCandidato": "INSCRITO",
            "strGuidFoto": "686cc1a6-f3fa-4598-916b-7e011518331e",
            "strNombre": "686cc1a6-f3fa-4598-916b-7e011518331e.jpg",
            "strUrlOrganizacionPolitica": "",
            "strCodExpedienteExt": "EG.2026015873",
            "idProcesoElectoral": 124,
            "strProcesoElectoral": "ELECCIONES GENERALES 2026",
            "idTipoEleccion": 21,
            "strTipoEleccion": "SENADORES DISTRITO MÚLTIPLE",
            "strAmbito": "NACIONAL",
            "strAnio_Eleccion": "2026",
            "strUbigeo": "170000",
            "strDepartamento": "MOQUEGUA",
            "strProvincia": ""
        },
        {
            "strDistrito": "",
            "idtipoorgpolitica": 5,
            "strTipoOrgPolitica": "ALIANZAS ELECTORALES",
            "idOrganizacionPolitica": 3023,
            "strOrganizacionPolitica": "UNIDAD NACIONAL",
            "idJuradoElectoralCreacion": 2103,
            "strJuradoElectoralCreacion": "MARISCAL NIETO",
            "intPosicion": 1,
            "idCargo": 16,
            "strCargo": "SENADOR",
            "strTipoDocumento": "DNI",
            "strDocumentoIdentidad": "40651290",
            "strNombres": "STALIN ELIZALDE",
            "strApellidoPaterno": "ZEBALLOS",
            "strApellidoMaterno": "RODRIGUEZ",
            "strSexo": "MASCULINO",
            "strFechaNacimiento": "30/06/1980 00:00:00",
            "strEsNativo": "NO",
            "strEstadoCandidato": "INSCRITO",
            "strGuidFoto": "0c6a71a0-9c77-4aca-9d6c-375a23610e4d",
            "strNombre": "0c6a71a0-9c77-4aca-9d6c-375a23610e4d.jpg",
            "strUrlOrganizacionPolitica": "",
            "strCodExpedienteExt": "EG.2026015873",
            "idProcesoElectoral": 124,
            "strProcesoElectoral": "ELECCIONES GENERALES 2026",
            "idTipoEleccion": 21,
            "strTipoEleccion": "SENADORES DISTRITO MÚLTIPLE",
            "strAmbito": "NACIONAL",
            "strAnio_Eleccion": "2026",
            "strUbigeo": "170000",
            "strDepartamento": "MOQUEGUA",
            "strProvincia": ""
        },
        {
            "strDistrito": "",
            "idtipoorgpolitica": 1,
            "strTipoOrgPolitica": "PARTIDOS POLITICOS",
            "idOrganizacionPolitica": 2930,
            "strOrganizacionPolitica": "PARTIDO APRISTA PERUANO",
            "idJuradoElectoralCreacion": 2103,
            "strJuradoElectoralCreacion": "MARISCAL NIETO",
            "intPosicion": 2,
            "idCargo": 16,
            "strCargo": "SENADOR",
            "strTipoDocumento": "DNI",
            "strDocumentoIdentidad": "15619140",
            "strNombres": "MONICA ELIZABETH",
            "strApellidoPaterno": "MAURICIO",
            "strApellidoMaterno": "BARRIENTOS",
            "strSexo": "FEMENINO",
            "strFechaNacimiento": "16/11/1975 00:00:00",
            "strEsNativo": "NO",
            "strEstadoCandidato": "INSCRITO",
            "strGuidFoto": "9a93236d-1afd-4685-b491-608452477914",
            "strNombre": "9a93236d-1afd-4685-b491-608452477914.jpg",
            "strUrlOrganizacionPolitica": "",
            "strCodExpedienteExt": "EG.2026016859",
            "idProcesoElectoral": 124,
            "strProcesoElectoral": "ELECCIONES GENERALES 2026",
            "idTipoEleccion": 21,
            "strTipoEleccion": "SENADORES DISTRITO MÚLTIPLE",
            "strAmbito": "NACIONAL",
            "strAnio_Eleccion": "2026",
            "strUbigeo": "170000",
            "strDepartamento": "",
            "strProvincia": ""
        },
        {
            "strDistrito": "",
            "idtipoorgpolitica": 1,
            "strTipoOrgPolitica": "PARTIDOS POLITICOS",
            "idOrganizacionPolitica": 2867,
            "strOrganizacionPolitica": "PARTIDO DEMOCRATA UNIDO PERU",
            "idJuradoElectoralCreacion": 2103,
            "strJuradoElectoralCreacion": "MARISCAL NIETO",
            "intPosicion": 1,
            "idCargo": 16,
            "strCargo": "SENADOR",
            "strTipoDocumento": "DNI",
            "strDocumentoIdentidad": "04648757",
            "strNombres": "NANCY KATERINE",
            "strApellidoPaterno": "BAUTISTA",
            "strApellidoMaterno": "ARROYO",
            "strSexo": "FEMENINO",
            "strFechaNacimiento": "24/03/1974 00:00:00",
            "strEsNativo": "NO",
            "strEstadoCandidato": "INSCRITO",
            "strGuidFoto": "73307104-6483-4212-bea9-a616dad0ec48",
            "strNombre": "73307104-6483-4212-bea9-a616dad0ec48.jpg",
            "strUrlOrganizacionPolitica": "",
            "strCodExpedienteExt": "EG.2026017449",
            "idProcesoElectoral": 124,
            "strProcesoElectoral": "ELECCIONES GENERALES 2026",
            "idTipoEleccion": 21,
            "strTipoEleccion": "SENADORES DISTRITO MÚLTIPLE",
            "strAmbito": "NACIONAL",
            "strAnio_Eleccion": "2026",
            "strUbigeo": "170000",
            "strDepartamento": "",
            "strProvincia": ""
        },
        {
            "strDistrito": "",
            "idtipoorgpolitica": 1,
            "strTipoOrgPolitica": "PARTIDOS POLITICOS",
            "idOrganizacionPolitica": 2961,
            "strOrganizacionPolitica": "PARTIDO DEL BUEN GOBIERNO",
            "idJuradoElectoralCreacion": 2103,
            "strJuradoElectoralCreacion": "MARISCAL NIETO",
            "intPosicion": 1,
            "idCargo": 16,
            "strCargo": "SENADOR",
            "strTipoDocumento": "DNI-E",
            "strDocumentoIdentidad": "02448030",
            "strNombres": "HUGO ISAIAS",
            "strApellidoPaterno": "QUISPE",
            "strApellidoMaterno": "MAMANI",
            "strSexo": "MASCULINO",
            "strFechaNacimiento": "16/12/1951 00:00:00",
            "strEsNativo": "NO",
            "strEstadoCandidato": "INSCRITO",
            "strGuidFoto": "faf841c6-b492-4c31-8741-3c1c5f10d33d",
            "strNombre": "faf841c6-b492-4c31-8741-3c1c5f10d33d.jpg",
            "strUrlOrganizacionPolitica": "",
            "strCodExpedienteExt": "EG.2026016152",
            "idProcesoElectoral": 124,
            "strProcesoElectoral": "ELECCIONES GENERALES 2026",
            "idTipoEleccion": 21,
            "strTipoEleccion": "SENADORES DISTRITO MÚLTIPLE",
            "strAmbito": "NACIONAL",
            "strAnio_Eleccion": "2026",
            "strUbigeo": "170000",
            "strDepartamento": "",
            "strProvincia": ""
        },
        {
            "strDistrito": "",
            "idtipoorgpolitica": 1,
            "strTipoOrgPolitica": "PARTIDOS POLITICOS",
            "idOrganizacionPolitica": 14,
            "strOrganizacionPolitica": "PARTIDO DEMOCRATICO SOMOS PERU",
            "idJuradoElectoralCreacion": 2103,
            "strJuradoElectoralCreacion": "MARISCAL NIETO",
            "intPosicion": 1,
            "idCargo": 16,
            "strCargo": "SENADOR",
            "strTipoDocumento": "DNI",
            "strDocumentoIdentidad": "04649069",
            "strNombres": "JOSE LUIS PEDRO",
            "strApellidoPaterno": "FERNANDEZ",
            "strApellidoMaterno": "CASTILLO",
            "strSexo": "MASCULINO",
            "strFechaNacimiento": "23/09/1956 00:00:00",
            "strEsNativo": "NO",
            "strEstadoCandidato": "INSCRITO",
            "strGuidFoto": "042f627a-d8ae-4387-82ef-74e2a2eadc46",
            "strNombre": "042f627a-d8ae-4387-82ef-74e2a2eadc46.jpg",
            "strUrlOrganizacionPolitica": "",
            "strCodExpedienteExt": "EG.2026016718",
            "idProcesoElectoral": 124,
            "strProcesoElectoral": "ELECCIONES GENERALES 2026",
            "idTipoEleccion": 21,
            "strTipoEleccion": "SENADORES DISTRITO MÚLTIPLE",
            "strAmbito": "NACIONAL",
            "strAnio_Eleccion": "2026",
            "strUbigeo": "170000",
            "strDepartamento": "MOQUEGUA",
            "strProvincia": ""
        }
    ],
    "type": 1,
    "message": "",
    "messageLog": "",
    "success": true,
    "aditional": 0,
    "extravalue": null,
    "fgVerificado": 0
}